Workbook

Sheet CRM
A1: FECHA PRIMER CONTACTO | B1: NOMBRE / APELLIDO | C1: TELÉFONO | D1: COMERCIO | E1: RUBRO | F1: LOCALIDAD | G1: CANAL DE ORIGEN | H1: PRODUCTO/S | I1: CONSULTA / VENTA | J1: MEDIO DE PAGO | K1: PLANES | L1: OBJECIONES | M1: OBSERVACIONES | N1: REBATIR OBJECIÓN | O1: SEGUIMIENTO | P1: FECHA ÚLTIMO CONTACTO | Q1: FECHA PRÓXIMO CONTACTO
A2: 46179 | B2: Encina Juan | C2: 3765 39-2770 | D2: Sí | E2: Emprendedor/a | F2: Posadas | G2: WhatsApp Directo | H2: Gaveta para dinero de 4 divisiones | I2: Venta | J2: Crédito Personal | K2: 10 semanas | L2: Sin Objeciones | M2: Pendiente a verficacion | O2: Pendiente | P2: 46179 | Q2: 46181
A3: 46179 | B3: Miguel Gonzalez | C3: 3743 45-2853 | D3: Sí | E3: Despensa | F3: Jardín América | G3: Campaña | H3: Multiprocesadora de alimentos y vegetales Santini TA-20 | I3: Consulta | J3: Combinado | K3: Sin Respuesta | L3: Evaluando | M3: Evaluando plan semanal y con tarjeta | O3: Esperando Respuesta | P3: 46179 | Q3: 46181
A4: 46178 | B4: Ruben Cristaldo | C4: 3751 52-8995 | D4: No | E4: Emprendedor/a | F4: Eldorado | G4: Seguimiento | H4: Horno Pizzero 3 moldes Danda Cincalum | I4: Venta | J4: Contado / Efectivo | K4: Contado | L4: Sin Objeciones | M4: Pendiente a entrega | O4: Pendiente | P4: 46178 | Q4: 46179
A5: 46176 | B5: Jesi ByR pizzeria | C5: 3764 24-6523 | D5: Sí | E5: Gastronomía | F5: Garupá | G5: Marketplace | H5: Envasadora al vacio TS-2500 | I5: Consulta | J5: Contado / Efectivo | K5: Contado | L5: Precio / Presupuesto | M5: No le convence el precio, esta averiguando en otros lugares | N5: Le ofreci desc efectivo | O5: Esperando Respuesta | P5: 46177 | Q5: 46178
A6: 46176 | B6: Guada | C6: 3751 25-7037 | D6: No | F6: Montecarlo | G6: Marketplace | H6: Freezer Inelro 215 lts | I6: Consulta | J6: Crédito Personal | K6: 10 semanas | L6: Consulta con 3ro | M6: No tiene comercio, pero sus papas si, tiene que consultar con ellos | O6: Esperando Respuesta | P6: 46177 | Q6: 46178
A7: 46175 | B7: Claudio | C7: 3764 62-7200 | D7: Sí | E7: Mini Market | F7: Posadas | G7: Marketplace | H7: Heladera exhibidora Briket M3030 | I7: Consulta | J7: Contado / Efectivo | K7: Contado | L7: Precio / Presupuesto | M7: Consiguio a mejor precio en Fravega | O7: Insatisfecho | P7: 46176 | Q7: 46204
A8: 46175 | B8: Claudia | C8: 3764 22-3559 | D8: Sí | E8: Emprendedor/a | F8: Posadas | G8: Referidos | H8: Envasadora al vacio | I8: Consulta | J8: Contado / Efectivo | K8: Contado | L8: Evaluando | M8: Evaluando opciones de equipos y precios | O8: Esperando Respuesta | P8: 46175 | Q8: 46176
A9: 46175 | B9: Cesar Maidana | C9: 3765 39-5560 | D9: Sí | E9: Carnicería | F9: Posadas | G9: Marketplace | H9: Sierra carnicera de mesa con picadora Seery | I9: Consulta | J9: Contado / Efectivo | K9: Contado | L9: Evaluando | M9: Esta buscando precios y comparando con otros lugares | N9: Le ofreci descuento abonando en efectivo | O9: Esperando Respuesta | P9: 46176 | Q9: 46179
A10: 46175 | B10: Emanuel Maciel | C10: 3794 06-8358 | D10: Sí | E10: Mini Market | F10: Posadas | G10: Marketplace | H10: Envasadora al vacio TS -1400 | I10: Pendiente a Cierre | J10: Crédito Personal | K10: 10 semanas | L10: Sin Objeciones | M10: No fue aprobado, esta en el veraz | O10: No Cumple con los Requisitos | P10: 46175 | Q10: 46175
A11: 46174 | B11: Florencia Montenegro | C11: 3764 58-5991 | D11: Sí | E11: Emprendedor/a | F11: Posadas | G11: Salón | H11: Panel ranurado 1,30x 1,80 mts | I11: Venta | J11: Contado / Efectivo | K11: Contado | L11: Sin Objeciones | M11: Entregado | O11: Entregado | P11: 46175 | Q11: 46176
A12: 46170 | B12: Sonia Perez | C12: 3764 63-8186 | D12: No | E12: Emprendedor/a | F12: Posadas | G12: Marketplace | H12: Envasadora al vacio TS 1200 | I12: Venta | J12: Tarjeta de Crédito | K12: Tarjeta | L12: Sin Objeciones | M12: Entregado | O12: Satisfecho | P12: 46172 | Q12: 46179
A13: 46170 | B13: Diego | C13: 3764 68-1227 | D13: Sí | E13: Autoservicio | F13: Posadas | G13: Marketplace | H13: Gondolas centrales y contrapared | I13: Consulta | J13: Contado / Efectivo | K13: Contado | L13: Evaluando | M13: Esta comparando precios | O13: Esperando Respuesta | P13: 46170 | Q13: 46171
A14: 46170 | B14: Maria Espinola | C14: 3754 47-5467 | D14: Sí | E14: Kiosco | F14: Leandro N. Alem | G14: Referidos | H14: Freezer vidrio curvo Briket 440 lts | I14: Venta | J14: Contado / Efectivo | K14: Contado | L14: Sin Objeciones | M14: Entregado | O14: Satisfecho | P14: 46170 | Q14: 46171
A15: 46170 | B15: Luzmila Simone | C15: 3764 89-3003 | D15: No | F15: Posadas | G15: Marketplace | H15: Cocina Sol Real 4 hornallas 535 VG | I15: Venta | J15: Contado / Efectivo | K15: Contado | L15: Sin Objeciones | M15: Lo seño para reservar | O15: Pendiente | P15: 46170 | Q15: 46179
A16: 46169 | B16: Francisco | C16: 3764 82-4677 | D16: Sí | E16: Panadería | F16: Posadas | G16: Salón | H16: Cortadora de fiambre Bianchi | I16: Consulta | J16: Contado / Efectivo | K16: Contado | L16: Evaluando | M16: No se es lo que esta buscando | N16: Le ofreci las opciones que tenemos | O16: Esperando Respuesta | P16: 46169 | Q16: 46170
A17: 46169 | B17: Marcelo BarTolome | C17: 3764 25-8096 | D17: Sí | E17: Gastronomía | F17: Posadas | G17: Salón | H17: Cortadora de fiambre Santini | I17: Consulta | J17: Crédito Personal | K17: Tarjeta | L17: Evaluando | M17: Sin stock, esperara que llegue de paso libera su tarjeta | O17: Pendiente | P17: 46172 | Q17: 46179
A18: 46169 | B18: Benitez Felipe/ Mariela | C18: 3764 17-6182 | D18: No | E18: Emprendedor/a | F18: Posadas | G18: Salón | H18: Horno 6 pizzas El Gauchito | I18: Venta | J18: Tarjeta de Crédito | K18: Tarjeta | L18: Sin Objeciones | M18: Entregado | O18: Entregado | P18: 46169 | Q18: 46174
A19: 46168 | B19: Marisa Rivero | C19: 3764 89-7570 | D19: Sí | E19: Kiosco | F19: Posadas | G19: Campaña | H19: Heladera mostrador equipada Peirano 1,90 mts | I19: Consulta | J19: Crédito Personal | K19: 10 semanas | L19: Evaluando | M19: Esta evaluando precios y mas equipos | O19: Esperando Respuesta | P19: 46168 | Q19: 46169
A20: 46168 | B20: Lisandro | C20: 3765 12-0942 | D20: Sí | E20: Panadería | F20: Posadas | G20: WhatsApp Directo | H20: Horno pastelero 24moldes | I20: Pendiente a Cierre | J20: Tarjeta de Crédito | K20: Tarjeta | L20: Consulta con 3ro | M20: Tiene que venir con el suegro, que es el dueño de la tarjeta. Vendria hoy en el trasncurso del dia | O20: Terminando de Cerrar | P20: 46169 | Q20: 46170
A21: 46168 | B21: Gustavo Skwarizski | C21: 3765 06-1473 | D21: Sí | E21: Gastronomía | F21: Garupá | G21: Salón | H21: Heladera Mostrador Bestcol Standard 1.60 | I21: Venta | J21: Tarjeta de Crédito | K21: Tarjeta | L21: Sin Objeciones | M21: Entregado | O21: Entregado | P21: 46169 | Q21: 46174
A22: 46164 | B22: Fatima Gonzalez | C22: 3757 31-0259 | D22: Sí | E22: Emprendedor/a | F22: Puerto Iguazú | G22: WhatsApp Directo | H22: Repulgadora cuadruple Ceico | I22: Venta | J22: Contado / Efectivo | K22: Contado | L22: Sin Objeciones | M22: Entregado | O22: Satisfecho | P22: 46171 | Q22: 46182
A23: 46164 | B23: Agus | C23: 3764 96-5827 | D23: Sí | E23: Gastronomía | F23: Posadas | G23: Referidos | H23: Amasadora rapida mixer 10 lts Moretti | I23: Consulta | J23: Contado / Efectivo | K23: Contado | L23: Consulta con 3ro | M23: Estan averiguando precios | O23: Esperando Respuesta | P23: 46164 | Q23: 46165
A24: 46164 | B24: Leandro Foss | C24: 3765 03-4826 | D24: Sí | E24: Carnicería | F24: Posadas | G24: WhatsApp Directo | H24: Gancho carnicero | I24: Venta | J24: Contado / Débito | K24: Contado | L24: Sin Objeciones | M24: Entregado | O24: Satisfecho | P24: 46165
A25: 46164 | B25: Juan | C25: 3764 20-1788 | D25: Sí | E25: Mini Market | F25: Posadas | G25: Marketplace | H25: Heladera exhibidora Briket M8000 794 lts | I25: Consulta | J25: Crédito Personal | L25: Inversión a Futuro | M25: Esta armando su local, todavia no lo abrio | O25: Esperando Respuesta | P25: 46164 | Q25: 46165
A26: 46163 | B26: Lorenzo | C26: 3765 22-0306 | D26: Sí | E26: Panadería | F26: Posadas | G26: Salón | H26: Bagueteras lisas perforadas | I26: Venta | J26: Crédito Personal | K26: 10 semanas | L26: Sin Objeciones | M26: Entregado | O26: Satisfecho | P26: 46171 | Q26: 46213
A27: 46163 | B27: Alberto Moreyra | C27: 3764633800 | D27: Sí | E27: Gastronomía | F27: Posadas | G27: Referidos | H27: Ralladora de queso Are 9 kg | I27: Venta | J27: Tarjeta de Crédito | K27: Tarjeta | L27: Sin Objeciones | M27: Entregado | O27: Satisfecho | P27: 46163 | Q27: 46174
A28: 46162 | B28: Sol Paraguay | C28: 595 981 064870 | D28: Sí | E28: Gastronomía | F28: Posadas | G28: Marketplace | H28: Multiprocesadora de alimentos y vegetales Santini TA-20 | I28: Consulta | J28: Crédito Personal | K28: 10 semanas | L28: Inversión a Futuro | M28: Cuando terminen el local realizara la compra | O28: Esperando Respuesta | P28: 46162 | Q28: 46174
A29: 46161 | B29: Yrma Silva | C29: 3765 20-9194 | D29: No | E29: Emprendedor/a | F29: Garupá | G29: Referidos | H29: 6 Moldes pizzeros moldes pan | I29: Venta | J29: Contado / Efectivo | K29: Contado | L29: Sin Objeciones | M29: Pendiente a entrega | O29: Pendiente | P29: 46161 | Q29: 46162
A30: 46161 | B30: Camila Ramirez/Pato M | C30: 3764 28-0347 | D30: Sí | E30: Emprendedor/a | F30: Posadas | G30: WhatsApp Directo | H30: Horno 12 pizzas El Gauchito y 30 moldes pizzeros | I30: Venta | J30: Contado / Efectivo | K30: Contado | L30: Sin Objeciones | M30: Entregado | O30: Satisfecho | P30: 46162 | Q30: 46162
A31: 46161 | B31: Gustavo Montecino | C31: 3764 86-2999 | D31: Sí | E31: Despensa | F31: San Vicente | G31: Seguimiento | H31: Heladera exhibidora MT980 Inelro | I31: Consulta | J31: Crédito Personal | K31: 10 semanas | L31: Inversión a Futuro | M31: Quiere esperar un poco mas, ya que estan bajas sus ventas | O31: Esperando Respuesta | P31: 46161 | Q31: 46174
A32: 46161 | B32: Cristina Alvez | C32: 3764688026 | D32: Sí | E32: Emprendedor/a | F32: Garupá | G32: Salón | H32: Horno Sol Real 8 pizzas | I32: Venta | J32: Tarjeta de Crédito | K32: Tarjeta | L32: Sin Objeciones | M32: Entregado | O32: Satisfecho | P32: 46162 | Q32: 46162
A33: 46160 | B33: Patricia | C33: 3764 10-0465 | D33: Sí | E33: Panadería | F33: Posadas | G33: Marketplace | H33: Heladera mostrador Patisserie | I33: Consulta | J33: Tarjeta de Crédito | K33: Tarjeta | L33: Evaluando | M33: Evaluando precio y opciones | O33: Esperando Respuesta | P33: 46161 | Q33: 46161
A34: 46160 | B34: Fer | C34: 3765 02-1117 | D34: No | F34: Posadas | G34: WhatsApp Directo | H34: Horno convector electrico Santini 4 bandejas | I34: Consulta | J34: Contado / Efectivo | K34: Contado | L34: Evaluando | M34: Vendra al local | O34: Esperando Respuesta | P34: 46160 | Q34: 46161
A35: 46160 | B35: Angelica | C35: 11 3101-6995 | D35: No | E35: Emprendedor/a | F35: Garuhapé | G35: Campaña | H35: Heladera exhibidora Briket 293 lts M3000 | I35: Consulta | J35: Contado / Efectivo | K35: Contado | L35: Evaluando | M35: Esta averiguando precios | O35: Esperando Respuesta | P35: 46160 | Q35: 46161
A36: 46160 | B36: Miguel | C36: 3764 86-6909 | D36: Sí | E36: Emprendedor/a | F36: Santo Tome | G36: WhatsApp Directo | H36: Freidora electrica doble anion | I36: Consulta | J36: Crédito Personal | K36: 10 semanas | L36: Evaluando | M36: Evaluando entre la simple y la doble | O36: Esperando Respuesta | P36: 46160 | Q36: 46161
A37: 46158 | B37: Liset Gomez | C37: 3765 12-9304 | D37: No | F37: Posadas | G37: Campaña | H37: Horno convector Santini 4 bandejas | I37: Consulta | J37: Tarjeta de Crédito | K37: Tarjeta | L37: Consulta con 3ro | M37: Lo hara con bienes durables el dia lunes, tiene que charlar con el esposo | O37: Esperando Respuesta | P37: 46158 | Q37: 46160
A38: 46157 | B38: Martin | C38: 3764 37-1490 | D38: Sí | E38: Emprendedor/a | F38: Posadas | G38: Campaña | H38: Heladera exhibidora y freezer | I38: Consulta | J38: Contado / Efectivo | K38: Contado | L38: Evaluando | M38: Compro usadas | O38: Insatisfecho | P38: 46161 | Q38: 46161
A39: 46157 | B39: Sol | C39: 3764 27-5778 | D39: No | F39: Posadas | G39: Marketplace | H39: Batidora planetaria Santini 7 litros | I39: Consulta | J39: Contado / Efectivo | K39: Contado | L39: Evaluando | M39: Vendra mañana al local | O39: Terminando de Cerrar | P39: 46157 | Q39: 46158
A40: 46157 | B40: Jorge | C40: 3751 56-4149 | D40: Sí | E40: Carnicería | F40: Eldorado | G40: Marketplace | H40: Envasadora al vacio TS-3500 | I40: Venta | J40: Tarjeta de Crédito | K40: Tarjeta | L40: Sin Objeciones | M40: Entregado | O40: Satisfecho | P40: 46175 | Q40: 46209
A41: 46157 | B41: Acacio Ayelen | C41: 3764 87-4811 | D41: Sí | E41: Kiosco | F41: Posadas | G41: Campaña | H41: Hel Mostrador equipada 1,90 mts | I41: Consulta | J41: Crédito Personal | K41: 20 semanas | L41: Sin Objeciones | M41: Se encuentra en el veraz | O41: No Cumple con los Requisitos | P41: 46157 | Q41: 46157
A42: 46157 | B42: Rios Cristian | C42: 3756 49-2643 | D42: Sí | E42: Despensa | F42: Santo Tome | G42: WhatsApp Directo | H42: Sierra carnicera de mesa | I42: Consulta | J42: Crédito Personal | K42: 10 semanas | L42: Evaluando | M42: Sin stock, le ofreci pedirlo con una seña del 30% | O42: Esperando Respuesta | P42: 46157 | Q42: 46160
A43: 46155 | B43: Leandro | C43: 3754 46-7873 | D43: Sí | E43: Kiosco | F43: Leandro N. Alem | G43: Campaña | H43: Freezer Briket 390 lts + Heladera Exh. Inelro 460 lts | I43: Consulta | J43: Contado / Efectivo | K43: Contado | L43: Evaluando | M43: Evaluando opciones de equipos y precios | O43: Esperando Respuesta | P43: 46155 | Q43: 46156
A44: 46155 | B44: Maria | C44: 3764 85-0551 | D44: Sí | E44: Emprendedor/a | F44: Garupá | G44: Marketplace | H44: Horno convector electrico Santini 4 bandejas | I44: Consulta | J44: Contado / Efectivo | K44: Contado | L44: Inversión a Futuro | M44: Recien para el mes que viene lo quiere | N44: Le ofreci señarlo y reservar | O44: Esperando Respuesta | P44: 46155 | Q44: 46172
A45: 46154 | B45: Leonardo | C45: 362 454-8993 | D45: No | F45: Leandro N. Alem | G45: Marketplace | H45: Cocina semi industrial 2 hornallas Danda | I45: Consulta | J45: Contado / Efectivo | K45: Contado | L45: Consulta con 3ro | M45: Vendra al local con su esposa a ver la cocina la semana que viene | O45: Esperando Respuesta | P45: 46160 | Q45: 46161
A46: 46154 | B46: Luis/ Asociacion de la mujer | C46: 3755 44-5907 | D46: Sí | E46: Emprendedor/a | F46: Posadas | G46: WhatsApp Directo | H46: Mesa de trabajo Sol Reak 1,50 mts | I46: Venta | J46: Contado / Débito | K46: Contado | L46: Sin Objeciones | M46: Entregado | O46: Satisfecho | P46: 46158 | Q46: 46158
A47: 46154 | B47: Laura | C47: 3743 45-2541 | D47: Sí | E47: Autoservicio | F47: Jardín América | G47: Marketplace | H47: Isla de frio Fam, Heladera exhibidora -18 Briket, pasillo de revision 1,50 mts | I47: Pendiente a Cierre | J47: Combinado | K47: Contado | L47: Inversión a Futuro | M47: Esta terminando el local, evaluara el metodo de pago | N47: Le envie las promos del hot sale | O47: Esperando Respuesta | P47: 46155 | Q47: 46158
A48: 46153 | B48: Adolfo | C48: 3786 41-3371 | D48: Sí | E48: Autoservicio | F48: Ituzaingó | G48: Marketplace | H48: Pasillo de revision 1,50 mts lado izquierdo | I48: Venta | J48: Crédito Personal | K48: 5 semanas | L48: Sin Objeciones | M48: Pendiente a entrega | O48: Pendiente | P48: 46155 | Q48: 46156
A49: 46153 | B49: Evelin Paola | C49: 3757 67-0267 | D49: Sí | E49: Polirubro | F49: Posadas | G49: Marketplace | H49: 3 tramos de gondola contrapared | I49: Consulta | J49: Crédito Personal | K49: 10 semanas | L49: Evaluando | M49: No tenemos stock de gondolas | O49: Esperando Respuesta | P49: 46175 | Q49: 46181
A50: 46153 | B50: Luis Alberto Gallardo | C50: 3764 17-5039 | D50: Sí | E50: Emprendedor/a | F50: Posadas | G50: Marketplace | H50: Cocina semi industrial 2 hornallas Danda | I50: Consulta | J50: Contado / Efectivo | K50: Contado | L50: Consulta con 3ro | M50: Tiene que consultarlo con la esposa y ver que metodo de pago les conviene | O50: Esperando Respuesta | P50: 46153 | Q50: 46154
A51: 46153 | B51: Marisa Salvador | C51: 3751 20-1007 | D51: Sí | E51: Despensa | F51: Eldorado | G51: Campaña | H51: Heladera exhibidora -4 Briket | I51: Consulta | J51: Crédito Personal | K51: 10 semanas | L51: Evaluando | M51: Evaluando la financiacion y precio de contado | N51: Quiere analizar un poco mas | O51: Esperando Respuesta | P51: 46154 | Q51: 46161
A52: 46141 | B52: Romina Santana | C52: 3764 63-4869 | D52: Sí | E52: Gastronomía | F52: Posadas | G52: Referidos | H52: Bnadejas aluminizadas y moldes pizzeros | I52: Venta | J52: Tarjeta de Crédito | K52: Tarjeta | L52: Sin Objeciones | M52: Pendiente a entrega | O52: Pendiente | P52: 46141 | Q52: 46142
A53: 46140 | B53: Guido Martinez | C53: 3764 12-4045 | D53: Sí | E53: Despensa | F53: Posadas | G53: Salón | H53: Freezer Briket 390 lts | I53: Venta | J53: Crédito Personal | K53: 10 semanas | L53: Sin Objeciones | M53: Pendiente a entrega | O53: Pendiente | P53: 46141 | Q53: 46141
A54: 46140 | B54: Meli Insaurralde | C54: 3735 44-6535 | D54: Sí | E54: Mini Market | F54: Chaco | G54: Marketplace | H54: 2 pasillos de revision 1,50 mts | I54: Consulta | J54: Contado / Débito | K54: Contado | L54: Evaluando | M54: Evaluando si pagar el envio o buscarlo | O54: Esperando Respuesta | P54: 46154 | Q54: 46161
A55: 46140 | B55: Gomez de Olivera Angel | C55: 11 6987-7018 | D55: Sí | E55: Autoservicio | F55: Cerro Azul | G55: Seguimiento | H55: Heladera exhibidora Inelro 460 lts | I55: Venta | J55: Crédito Personal | K55: 5 semanas | L55: Sin Objeciones | M55: Plan diferido. Equipo entregado | O55: Satisfecho | P55: 46154 | Q55: 46177
A56: 46140 | B56: Alexander | C56: 3754 65-9654 | D56: Sí | E56: Autoservicio | F56: Leandro N. Alem | G56: Referidos | H56: Gondola central, cortadora de fiambre Santini y freezer para helados 279 lts Inelro | I56: Consulta | J56: Crédito Personal | K56: 10 semanas | L56: Evaluando | M56: Faltan los requisitos | O56: Esperando Respuesta | P56: 46141 | Q56: 46141
A57: 46140 | B57: Rodolfo Drewanz | C57: 3764 37-7149 | D57: Sí | E57: Gastronomía | F57: Garupá | G57: Salón | H57: Horno 12 pizzas El Gauchito | I57: Venta | J57: Tarjeta de Crédito | K57: Tarjeta | L57: Sin Objeciones | M57: Entregado | O57: Satisfecho | P57: 46140 | Q57: 46142
A58: 46139 | B58: Luisa Frank | C58: 3764369042 | D58: Sí | E58: Gastronomía | F58: Garupá | G58: Salón | H58: Horno Convector Santini 3 bandejas MC-840 | I58: Venta | J58: Contado / Efectivo | K58: Contado | L58: Sin Objeciones | M58: Entregado | O58: Satisfecho | P58: 46140 | Q58: 46141
A59: 46137 | B59: Miguel Diaz | C59: 3764 20-3783 | D59: Sí | E59: Mini Market | F59: Posadas | G59: Marketplace | H59: Gondola de frio abierta Frider | I59: Consulta | J59: Contado / Efectivo | K59: Contado | L59: Evaluando | M59: No tenemos stock del modelo que busca el cliente | N59: Le ofreci traerlo por pedido | O59: Esperando Respuesta | P59: 46139 | Q59: 46140
A60: 46136 | B60: Maria Lujan Fibig | C60: 3758 54-4498 | D60: Sí | E60: Kiosco | F60: Apóstoles | G60: WhatsApp Directo | H60: Heladera exhibidora Briket 293 lts M3000 | I60: Consulta | J60: Crédito Personal | K60: 10 semanas | L60: Evaluando | M60: No cumple con los requisitos para financiar | N60: Le ofreci descuento de contado, lo esta evaluando | O60: No Cumple con los Requisitos | P60: 46136 | Q60: 46146
A61: 46135 | B61: Luciana Belling | C61: 3755 45-7708 | D61: No | F61: San Vicente | G61: Campaña | H61: Picadora de carne Toppari | I61: Consulta | J61: Contado / Efectivo | K61: Contado | L61: Consulta con 3ro | M61: Lo tiene que charlar con el esposo | N61: Consiguieron a mejor precio en la competencia | O61: Esperando Respuesta | P61: 46139 | Q61: 46153
A62: 46135 | B62: Leandro Bonus | C62: 3764 74-1641 | D62: Sí | E62: Gastronomía | F62: Posadas | G62: WhatsApp Directo | H62: Envasadora al vacio TS-1400 y dispenser para rollo portafilm | I62: Venta | J62: Tarjeta de Crédito | K62: Tarjeta | L62: Sin Objeciones | M62: Entregado | N62: Consulto por estantes para hel exhibidora y bandejas mc 600 | O62: Satisfecho | P62: 46135 | Q62: 46136
A63: 46135 | B63: Melany Acuña | C63: 3765 24-2816 | D63: Sí | E63: Gastronomía | F63: Posadas | G63: Referidos | H63: Freezer Inelro tapa ciega | I63: Consulta | J63: Contado / Débito | K63: Contado | L63: Evaluando | M63: Consiguio a mejor precio | O63: Insatisfecho | P63: 46139 | Q63: 46140
A64: 46134 | B64: Daniel Mayol | C64: 3764 51-9505 | D64: Sí | E64: Gastronomía | F64: Posadas | G64: Referidos | H64: Amasadora mb 7 kg | I64: Consulta | J64: Tarjeta de Crédito | K64: Tarjeta | L64: Inversión a Futuro | M64: Cuando libere su tarjeta | O64: Esperando Respuesta | P64: 46135 | Q64: 46139
A65: 46134 | B65: Mario Scoccia | C65: 3764 58-5028 | D65: Sí | E65: Gastronomía | F65: Posadas | G65: WhatsApp Directo | H65: Heladera exhibidora Briket 417 lts | I65: Venta | J65: Contado / Efectivo | K65: Contado | L65: Sin Objeciones | M65: Abona seña y pasa a abonar el total el 24/04 | O65: Pendiente | P65: 46134 | Q65: 46136
A66: 46134 | B66: Pablo | C66: 3764 10-5656 | D66: Sí | E66: Emprendedor/a | F66: Posadas | G66: WhatsApp Directo | H66: Freidora electrica doble anion | I66: Pendiente a Cierre | J66: Tarjeta de Crédito | K66: Tarjeta | L66: Evaluando | M66: Viene mañana | O66: Terminando de Cerrar | P66: 46141 | Q66: 46142
A67: 46132 | B67: Noir Marcos | C67: 11 6704-5140 | D67: Sí | E67: Emprendedor/a | F67: Posadas | G67: Marketplace | H67: Envasadora al vacio TS-1200 | I67: Venta | J67: Contado / Efectivo | K67: Contado | L67: Sin Objeciones | M67: Entregado | O67: Satisfecho | P67: 46134 | Q67: 46135
A68: 46133 | B68: David | C68: 3764 58-9912 | D68: Sí | E68: Emprendedor/a | F68: Posadas | G68: Marketplace | H68: Fabricadora de hielo Innova 250 kg | I68: Consulta | J68: Contado / Efectivo | K68: Contado | L68: Evaluando | M68: No le fue aprobado el credito y no cuenta con el dinero | O68: No Cumple con los Requisitos | P68: 46134 | Q68: 46134
A69: 46133 | B69: Lorena | C69: 11 3453-0759 | D69: No | F69: Apóstoles | G69: Campaña | H69: Cortadora de fiambre Bianchi | I69: Consulta | J69: Contado / Efectivo | K69: Contado | L69: Consulta con 3ro | M69: Lo tiene que ver con la familia, ya que es para un emprendimiento familiar | N69: Le pase la opcion de la Santini | O69: Esperando Respuesta | P69: 46136 | Q69: 46139
A70: 46133 | B70: Vanesa | C70: 3764 69-9869 | D70: No | F70: Posadas | G70: Marketplace | H70: Horno convector Santini de 4 bandejas | I70: Consulta | J70: Contado / Efectivo | K70: Contado | L70: Consulta con 3ro | M70: Lo charlara con el esposo | O70: Esperando Respuesta | P70: 46135 | Q70: 46136
A71: 46133 | B71: Flabia Alvarez | C71: 3758 40-0526 | D71: Sí | E71: Despensa | F71: Corrientes | G71: WhatsApp Directo | H71: Batea 1,20 mts | I71: Consulta | J71: Crédito Personal | K71: 15 semanas | L71: Consulta con 3ro | M71: Lo charlara con el esposo | N71: Sin respuesta al primer seg. Intentar con llamada | O71: Esperando Respuesta | P71: 46135 | Q71: 46136
A72: 46132 | B72: Pablo | C72: 3764 41-5915 | D72: Sí | E72: Emprendedor/a | F72: Posadas | G72: Referidos | H72: Amasadora rapida Moretti mixer 10 | I72: Consulta | J72: Contado / Efectivo | K72: Contado | L72: Consulta con 3ro | M72: Lo tiene que evaluar con la socia | O72: Esperando Respuesta | P72: 46132 | Q72: 46135
A73: 46132 | B73: Lisandro Scarso | C73: 11 5871-7032 | D73: Sí | E73: Emprendedor/a | F73: Posadas | G73: Marketplace | H73: Multiprocesadora de alimentos y vegetales Santini TA-20 | I73: Venta | J73: Contado / Efectivo | K73: Contado | L73: Sin Objeciones | M73: Producto entregado | O73: Satisfecho | P73: 46134 | Q73: 46146
A74: 46132 | B74: Hector | C74: 3765 02-6900 | D74: Sí | E74: Despensa | F74: San Ignacio | G74: WhatsApp Directo | H74: Heladera mostrador equipada 1,60 | I74: Consulta | J74: Crédito Personal | K74: 15 semanas | L74: Consulta con 3ro | M74: Lo charlara con la esposa, tendria una respuesta para el viernes | O74: Esperando Respuesta | P74: 46132 | Q74: 46136
A75: 46132 | B75: Cristian | C75: 3764 73-4789 | D75: Sí | E75: Despensa | F75: Posadas | G75: Marketplace | H75: Heladera mostrador standard 1,60 | I75: Consulta | J75: Crédito Personal | K75: 10 semanas | L75: Precio / Presupuesto | M75: Evaluando precio y opciones | O75: Esperando Respuesta | P75: 46135 | Q75: 46137
A76: 46132 | B76: Analia | C76: 3764 82-5592 | D76: No | F76: Candelaria | G76: Marketplace | H76: Horno Convector Santini 4 bandejas | I76: Consulta | J76: Tarjeta de Crédito | K76: Tarjeta | L76: Consulta con 3ro | M76: Tiene que venir al local para hacer con ahora bienes | N76: Lo tiene que charlar con el esposo | O76: Esperando Respuesta | P76: 46133 | Q76: 46137
A77: 46130 | B77: Luli | C77: 3757 55-2054 | D77: No | F77: Puerto Iguazú | G77: Marketplace | H77: Horno Electrico Convector Santini 4 bandejas | I77: Consulta | J77: Contado / Débito | K77: Contado | L77: Evaluando | M77: Evaluara si hacerlo de contado o con tarjeta | N77: Sin respuesta | O77: Esperando Respuesta | P77: 46132 | Q77: 46133
A78: 46130 | B78: Tonarelli Francisco | D78: No | F78: Posadas | G78: Marketplace | H78: Cocina Sol Real Multifuncion 2 hornallas con plancha y carlitero | I78: Venta | J78: Contado / Débito | K78: Contado | L78: Sin Objeciones | M78: Entregado | O78: Satisfecho | P78: 46130 | Q78: 46132
A79: 46129 | B79: Veronica Schiaffino | C79: 3764 69-5387 | D79: Sí | E79: Particular | F79: Posadas | G79: Campaña | H79: Heladera exhibidora vertical Inelro 460 lts | I79: Consulta | J79: Tarjeta de Crédito | K79: Tarjeta | L79: Evaluando | M79: Evaluando cuotas con naranja y macro | O79: Esperando Respuesta | P79: 46135 | Q79: 46137
A80: 46128 | B80: Manuel | C80: 3756 51-2484 | D80: No | E80: Carnicería | F80: Santo Tome | G80: WhatsApp Directo | H80: Batea 2,40 mts y Sierra carnicera | I80: Consulta | J80: Crédito Personal | K80: 15 semanas | L80: Evaluando | M80: No cumple con los requisitos | N80: Le ofreci pagar, luego retirar | O80: Esperando Respuesta | P80: 46133 | Q80: 46134

Sheet CONTEO
A2: FECHA | B2: MES | C2: MEDIO | D2: ORIGEN | E2: VENTA CERRADA | F2: CRM | G2: CLIENTE
A3: 46179 | C3: Salón | D3: Seguimiento WhatsApp | E3: No | F3: Sí | G3: Existente
A4: 46179 | C4: Salón | D4: Salón | E4: No | F4: No | G4: Nuevo
A5: 46179 | C5: Online | D5: WhatsApp Directo | E5: Sí | F5: Sí | G5: Nuevo
A6: 46179 | C6: Online | D6: Campaña RRSS | E6: No | F6: Sí | G6: Nuevo
A7: 46179 | C7: Online | D7: Seguimiento WhatsApp | E7: No | F7: Sí | G7: Nuevo
A8: 46179 | C8: Online | D8: Marketplace Face | E8: No | F8: No | G8: Nuevo
A9: 46179 | C9: Online | D9: Seguimiento WhatsApp | E9: No | F9: Sí | G9: Nuevo
A10: 46179 | C10: Online | D10: WhatsApp Directo | E10: No | F10: No | G10: Nuevo
A11: 46178 | C11: Online | D11: Referidos | E11: Sí | F11: Sí | G11: Nuevo
A12: 46178 | C12: Online | D12: Seguimiento WhatsApp | E12: Sí | F12: Sí | G12: Nuevo
A13: 46178 | C13: Online | D13: Seguimiento WhatsApp | E13: No | F13: Sí | G13: Existente
A14: 46178 | C14: Online | D14: Seguimiento WhatsApp | E14: No | F14: Sí | G14: Existente
... A359: 46109 | C359: Online | D359: Seguimiento WhatsApp | E359: No | F359: Sí | G359: Nuevo
A360: 46108 | B360: =A360 -> 46108 | C360: Online | D360: Marketplace Face | E360: Sí | F360: Sí | G360: Nuevo
A361: 46108 | B361: =A361 -> 46108 | C361: Salón | D361: Salón | E361: No | F361: No | G361: Nuevo
A362: 46108 | B362: =A362 -> 46108 | C362: Online | D362: Marketplace Face | E362: No | F362: No | G362: Nuevo
A363: 46108 | B363: =A363 -> 46108 | C363: Online | D363: Seguimiento WhatsApp | E363: No | F363: Sí | G363: Existente
A364: 46107 | B364: =A364 -> 46107 | C364: Online | D364: Seguimiento WhatsApp | E364: No | F364: Sí | G364: Existente
A365: 46107 | B365: =A365 -> 46107 | C365: Online | D365: Marketplace Face | E365: No | F365: No | G365: Nuevo
A366: 46107 | B366: =A366 -> 46107 | C366: Online | D366: Marketplace Face | E366: No | F366: No | G366: Nuevo
A367: 46107 | B367: =A367 -> 46107 | C367: Online | D367: WhatsApp Directo | E367: No | F367: No | G367: Existente
A368: 46107 | B368: =A368 -> 46107 | C368: Online | D368: Seguimiento WhatsApp | E368: Sí | F368: Sí | G368: Nuevo
A369: 46107 | B369: =A369 -> 46107 | C369: Online | D369: Seguimiento WhatsApp | E369: No | F369: Sí | G369: Existente
A370: 46107 | B370: =A370 -> 46107 | C370: Online | D370: Seguimiento WhatsApp | E370: No | F370: Sí | G370: Existente
A371: 46107 | B371: =A371 -> 46107 | C371: Online | D371: Seguimiento WhatsApp | E371: No | F371: Sí | G371: Nuevo
... A438: 46092 | B438: =A438 -> 46092 | C438: Online | D438: Campaña RRSS | E438: No | F438: No | G438: Nuevo
B1120: =A1120 -> 0
B1121: =A1121 -> 0
B1122: =A1122 -> 0
B1123: =A1123 -> 0
B1124: =A1124 -> 0
B1125: =A1125 -> 0
B1126: =A1126 -> 0
B1127: =A1127 -> 0
B1128: =A1128 -> 0
B1129: =A1129 -> 0
B1130: =A1130 -> 0
B1131: =A1131 -> 0
... B1303: =A1303 -> 0
A1304: 45992 | B1304: =A1304 -> 45992 | C1304: Online | D1304: WhatsApp Directo
B1305: =A1305 -> 0
B1306: =A1306 -> 0
B1307: =A1307 -> 0
B1308: =A1308 -> 0
B1309: =A1309 -> 0
B1310: =A1310 -> 0
B1311: =A1311 -> 0
B1312: =A1312 -> 0
B1313: =A1313 -> 0
B1314: =A1314 -> 0

Sheet PROYECTADO
A2: OCTUBRE | B2: DIA ACTUAL | C2: SOFIA
A3: 23 | B3: 9 | C3: OBJETIVO | D3: VENDIDO | F3: % PROYECTADO | G3: DIF. vs OBJ.
A4: ARTICULOS | C4: 8000000 | D4: =C26 -> 14866587 | F4: =(D4/C4)*1 -> 1.8583234 | G4: =D4-C4 -> 6866587
A5: EFECTIVO | C5: 1000000 | D5: =H26 -> 270000 | F5: =(D5/C5)*1 -> 0.27 | G5: =D5-C5 -> -730000
A9: ARTICULOS: | G9: MCP
A10: 1 | B10: heladera exhibidora | C10: 1492460 | D10: 45927 | G10: 1 | H10: 270000
A11: 1 | B11: freezer 279 lts | C11: 1010219 | D11: 45932
A12: 1 | B12: lavarropas 5kg | C12: 375750 | D12: 45932
A13: 1 | B13: freezer 135 lts | C13: 775371 | D13: 45933
A14: 1 | B14: moldes pizza (10) | C14: 49210 | D14: 45936
A15: 1 | B15: multiprocesadora santini | C15: 990000 | D15: 45938
A16: 1 | B16: Hamburguesera facil ceico | C16: 46950 | D16: 45938
A17: 1 | B17: Horno 3 moldes pizzero | C17: 313811 | D17: 45947
A18: 1 | B18: Freezer inelro 455 lts | C18: 1415815 | D18: 45954
A19: 1 | B19: balanza Moretti | C19: 318822 | D19: 45955
A20: 1 | B20: Impresora Moretti | C20: 208603 | D20: 42302
A21: 1 | B21: Freezer helados Inelro | C21: 1184918 | D21: 45957
A22: 2 | B22: Moldes pizza (2) | C22: 21138 | D22: 45957
... A25: 1 | B25: Balanza y impresora | C25: 527430 | D25: 45960
A26: =SUM(A10:A25) -> 17 | C26: =SUM(C10:C25) -> 14866587 | G26: =G10+G11+G12+G13 -> 1 | H26: =SUM(H10:H16) -> 270000
A29: NOVIEMBRE | B29: DIA ACTUAL | C29: SOFIA
A30: DICIEMBRE | B30: 1 | C30: OBJETIVO | D30: VENDIDO | F30: % PROYECTADO | G30: DIF. vs OBJ.
A31: ENERO | C31: 15000000 | D31: 8986218 | F31: =(D31/C31)*1 -> 0.5990812 | G31: =D31-C31 -> -6013782
A32: FEBRERO | C32: 2000000 | D32: 270000 | F32: =(D32/C32)*1 -> 0.135 | G32: =D32-C32 -> -1730000
K34: Del 31/10 al jueves 27/11
A36: ARTICULOS: | G36: MCP
A37: CANTIDAD | B37: FECHA | C37: TOTAL $$ | G37: CLIENTE | H37: FECHA | I37: TOTAL $$
A38: 30 | B38: 45964 | C38: 137790 | G38: Nestor Peralta | H38: 45981 | I38: 270000
A39: 1 | B39: 45965 | C39: 38260
A40: 1 | B40: 45971 | C40: 656250
A41: 1 | B41: 45973 | C41: 3427800
A42: 1 | B42: 45975 | C42: 58300
A43: 1 | B43: 45976 | C43: 18876
A44: 1 | B44: 45982 | C44: 1619070
A45: 1 | B45: 45982 | C45: 662620
A46: 1 | B46: 45984 | C46: 841460
A47: 1 | B47: 45986 | C47: 179000
A49: 1 | B49: 45988 | C49: 1346792
A50: =SUM(A37:A49) -> 40 | C50: =SUM(C37:C49) -> 8986218 | I50: =I38+I39+I40+I41+I42+I43 -> 270000
A55: DICIEMBRE | B55: DIA ACTUAL | C55: SOFIA
A56: 21 | C56: OBJETIVO | D56: VENDIDO | F56: % PROYECTADO | G56: DIF. vs OBJ.
A57: ARTICULOS | C57: 19000000 | D57: 20208140 | F57: =(D57/C57)*1 -> 1.0635863 | G57: =D57-C57 -> 1208140
A58: EFECTIVO | C58: 2000000 | F58: =(D58/C58)*1 -> 0 | G58: =D58-C58 -> -2000000
A61: ARTICULOS: | G61: MCP
A62: CANTIDAD | B62: FECHA | C62: TOTAL $$ | G62: CLIENTE | H62: FECHA | I62: TOTAL $$
A63: 1 | B63: 45987 | C63: 1718330
A64: 1 | B64: 45993 | C64: 1019320
A65: 1 | B65: 45989 | C65: 1633528
A66: 1 | B66: 45989 | C66: 1619070
A67: 1 | B67: 45992 | C67: 4104973
A68: 1 | B68: 45973 | C68: 3672130
A69: 1 | B69: 45995 | C69: 139380
A70: 1 | B70: 45996 | C70: 353662
A71: 1 | B71: 46000 | C71: 159660
A72: 1 | B72: 46003 | C72: 690000
A73: 1 | B73: 46003 | C73: 516390
A74: 1 | B74: 46007 | C74: 118301.83
... A82: 1 | B82: 46021 | C82: 45080
I83: =I63+I64+I65+I66+I67+I68 -> 0
A86: ENERO | B86: DIA ACTUAL | C86: SOFIA
A87: 19 | B87: 11 | C87: OBJETIVO | D87: VENDIDO | F87: % PROYECTADO | G87: DIF. vs OBJ.
A88: ARTICULOS | C88: 25000000 | D88: 24362636 | F88: =(D88/C88)*1 -> 0.97450544 | G88: =D88-C88 -> -637364
A89: EFECTIVO | C89: 6500000 | D89: 1030000 | F89: =(D89/C89)*1 -> 0.15846154 | G89: =D89-C89 -> -5470000
A93: ARTICULOS: | H93: MCP
A94: CANTIDAD | B94: FECHA | C94: TOTAL $$ | H94: FECHA | I94: TOTAL $$
A95: 4 | B95: 46028 | C95: 8588800 | H95: 46036 | I95: 640000
A96: 1 | B96: 46028 | C96: 1384230 | H96: 46037 | I96: 390000
A97: 1 | B97: 46028 | C97: 611975
A98: 1 | B98: 46034 | C98: $934.311.68
A99: 1 | B99: 46035 | C99: 1004473.7
A100: 1 | B100: 46035 | C100: 712225
A101: 1 | B101: 46039 | C101: 15534
A102: 1 | B102: 46039 | C102: 44160
A103: 1 | B103: 46039 | C103: 1766508
A104: 1 | B104: 46041 | C104: 645636.07
A105: 1 | B105: 46046 | C105: 193230.42
A106: 1 | B106: 46046 | C106: 355025
A107: 1 | B107: 46044 | C107: 143825
A108: 1 | B108: 46048 | C108: 188842
A109: 1 | B109: 46049 | C109: 2100000
A110: 1 | B110: 46049 | C110: 144126
... A118: 1 | B118: 46051 | C118: 543085
A126: FEBRERO | B126: DIA ACTUAL | C126: SOFIA
A127: 18 | B127: 18 | C127: OBJETIVO | D127: VENDIDO | F127: % PROYECTADO | G127: DIF. vs OBJ. | I127: Muy bien sofi :)
A128: ARTICULOS | C128: 26000000 | D128: 25492227 | F128: =(D128/C128)*1 -> 0.98047027 | G128: =D128-C128 -> -507773 | I128: Excelente Sofi vos podes mi chica 10
A129: EFECTIVO | C129: 3000000 | D129: 0 | F129: =(D129/C129)*1 -> 0 | G129: =D129-C129 -> -3000000
A132: ARTICULOS | G132: MCP | J132: CONTADO | K132: TARJETA | L132: FINANCIADO
A133: CANTIDAD | B133: FECHA | C133: TOTAL$$ | G133: FECHA | H133: TOTAL | J133: 4955464 | K133: 3951312.9 | L133: 13222580
A134: 1 | B134: 46056 | C134: 44160
A135: 1 | B135: 46058 | C135: 160322
A136: 1 | B136: 46058 | C136: 388774.21
A137: 1 | B137: 46059 | C137: 168557.35
A138: 1 | B138: 46060 | C138: 3393981.4
A139: 1 | B139: 46060 | C139: 2039845
A140: 1 | B140: 46062 | C140: 1612355
A141: 1 | B141: 46063 | C141: 684080
A142: 1 | B142: 46066 | C142: 1138900
A143: 1 | B143: 46066 | C143: 659157
A144: 1 | B144: 46071 | C144: 684075
A145: 1 | B145: 46072 | C145: 683825
...

Sheet MARZO 2026
A1: PERÍODO: 27/02/26 AL 26/03/26 | DÍAS HÁBILES: 19 | SÁBADOS (½): 3 | FERIADO: 1 (24/03) | M1: TOTAL VENDIDO | N1: CONTADO | O1: TARJETA / CHEQUE | P1: FINANCIADO | Q1: MCP | R1: OBJETIVO MENSUAL | T1: MÍNIMO A VENDER
A2: N° DÍA | B2: FECHA DE VENTA | C2: APELLIDO Y NOMBRE | D2: MONTO FICHA | E2: FORMA | F2: COMISIÓN (%) | G2: COMISIÓN ($) | H2: ENTREGADO | I2: SISTEMA | J2: FECHA DE CARGA EN EL SISTEMA | K2: CLIENTE | M2: =SUM(D:D) -> 25154837 | N2: =SUMIF($E:$E,N1,$D:$D) -> 6940041 | O2: =SUMIF($E:$E,O1,$D:$D) -> 10599176 | P2: =SUMIF($E:$E,P1,$D:$D) -> 7615620 | Q2: =SUMIF($E:$E,Q1,$D:$D) -> 0 | R2: =M2/S2 -> 0.96749371 | S2: 26000000 | T2: =(N2+O2+P2+(Q2/2))/U2 -> 1.8523444 | U2: 13580000
A3: 1 | B3: 46083 | C3: ANTONIO CORTEZ | D3: 160322 | E3: CONTADO | F3: =IF(E3="CONTADO", 4%, IF(E3="TARJETA / CHEQUE", 3%, IF(E3="FINANCIADO", 2.5%, ""))) -> 0.04 | G3: =IF(F3="", "", F3*D3) -> 6412.88 | H3: =TRUE() -> TRUE | I3: =TRUE() -> TRUE | J3: 46083 | K3: NUEVO | R3: RESTANTE | S3: =S2-M2 -> 845163.48 | T3: RESTANTE | U3: =IF((U2-M2)>=0,U2-M2,"")
A4: 1 | B4: 46083 | C4: ANTONIO BELFIORE | D4: 1884830 | E4: CONTADO | F4: =IF(E4="CONTADO", 4%, IF(E4="TARJETA / CHEQUE", 3%, IF(E4="FINANCIADO", 2.5%, ""))) -> 0.04 | G4: =IF(F4="", "", F4*D4) -> 75393.2 | H4: =TRUE() -> TRUE | I4: =TRUE() -> TRUE | J4: 46083 | K4: NUEVO
A5: 1 | B5: 46084 | C5: GOMEZ DE OLIVERA CARLOS ANGEL | D5: 3583430 | E5: FINANCIADO | F5: =IF(E5="CONTADO", 4%, IF(E5="TARJETA / CHEQUE", 3%, IF(E5="FINANCIADO", 2.5%, ""))) -> 0.025 | G5: =IF(F5="", "", F5*D5) -> 89585.75 | H5: =TRUE() -> TRUE | I5: =TRUE() -> TRUE | J5: 46084 | K5: EXISTENTE | M5: LOCALIDAD | R5: COBRADOR | T5: ANTICIPO SI ES NUEVO
A6: 2 | B6: 46084 | C6: DE OLIVEIRA TERESITA HELENA | D6: 520040 | E6: FINANCIADO | F6: =IF(E6="CONTADO", 4%, IF(E6="TARJETA / CHEQUE", 3%, IF(E6="FINANCIADO", 2.5%, ""))) -> 0.025 | G6: =IF(F6="", "", F6*D6) -> 13001 | H6: =TRUE() -> TRUE | I6: =TRUE() -> TRUE | J6: 46086 | K6: NUEVO | M6: Profundidad | R6: =IFERROR(VLOOKUP(M6,BD!H:J,2,FALSE()),"") -> Online - ZONA 20 | T6: =IFERROR(VLOOKUP(M6,BD!H:J,3,FALSE()),"") -> 30%
A7: 2 | B7: 46084 | C7: RICARDO MARTIN SANCHEZ | D7: 996044.93 | E7: TARJETA / CHEQUE | F7: =IF(E7="CONTADO", 4%, IF(E7="TARJETA / CHEQUE", 3%, IF(E7="FINANCIADO", 2.5%, ""))) -> 0.03 | G7: =IF(F7="", "", F7*D7) -> 29881.348 | H7: =TRUE() -> TRUE | I7: =TRUE() -> TRUE | J7: 46086 | K7: NUEVO
A8: 2 | B8: 46085 | C8: OFELIA SOSA | D8: 343845 | E8: FINANCIADO | F8: =IF(E8="CONTADO", 4%, IF(E8="TARJETA / CHEQUE", 3%, IF(E8="FINANCIADO", 2.5%, ""))) -> 0.025 | G8: =IF(F8="", "", F8*D8) -> 8596.125 | H8: =TRUE() -> TRUE | I8: =TRUE() -> TRUE | J8: 46084 | K8: EXISTENTE
A9: 8 | B9: 46091 | C9: CORDEIRO RAMON CESAR | D9: 1364055 | E9: FINANCIADO | F9: =IF(E9="CONTADO", 4%, IF(E9="TARJETA / CHEQUE", 3%, IF(E9="FINANCIADO", 2.5%, ""))) -> 0.025 | G9: =IF(F9="", "", F9*D9) -> 34101.375 | H9: =TRUE() -> TRUE | I9: =TRUE() -> TRUE | J9: 46097 | K9: NUEVO
A10: 8 | B10: 46091 | C10: SILVA HECTOR SALVADOR | D10: 4048396.1 | E10: TARJETA / CHEQUE | F10: =IF(E10="CONTADO", 4%, IF(E10="TARJETA / CHEQUE", 3%, IF(E10="FINANCIADO", 2.5%, ""))) -> 0.03 | G10: =IF(F10="", "", F10*D10) -> 121451.88 | H10: =TRUE() -> TRUE | I10: =TRUE() -> TRUE | J10: 46094 | K10: NUEVO
A11: 12 | B11: 46097 | C11: CLARISA DRESH | D11: 672918 | E11: CONTADO | F11: =IF(E11="CONTADO", 4%, IF(E11="TARJETA / CHEQUE", 3%, IF(OR(E11="FINANCIADO", E11="MCP"), 2.5%, ""))) -> 0.04 | G11: =IF(F11="", "", F11*D11) -> 26916.72 | H11: =TRUE() -> TRUE | I11: =TRUE() -> TRUE | J11: 46098 | K11: EXISTENTE
A12: 14 | B12: 46099 | C12: ACOSTA FABIAN EDUARDO | D12: 2340350 | E12: CONTADO | F12: =IF(E12="CONTADO", 4%, IF(E12="TARJETA / CHEQUE", 3%, IF(OR(E12="FINANCIADO", E12="MCP"), 2.5%, ""))) -> 0.04 | G12: =IF(F12="", "", F12*D12) -> 93614 | H12: =TRUE() -> TRUE | I12: =TRUE() -> TRUE | J12: 46106 | K12: NUEVO
A13: 16 | B13: 46101 | C13: JANSAT VICTOR EZEQUIEL | D13: 1804250 | E13: FINANCIADO | F13: =IF(E13="CONTADO", 4%, IF(E13="TARJETA / CHEQUE", 3%, IF(OR(E13="FINANCIADO", E13="MCP"), 2.5%, ""))) -> 0.025 | G13: =IF(F13="", "", F13*D13) -> 45106.25 | H13: =TRUE() -> TRUE | I13: =TRUE() -> TRUE | J13: 46107 | K13: EXISTENTE
A14: 16 | B14: 46101 | C14: MARTIN JOSE ROBERTO | D14: 1500000 | E14: CONTADO | F14: =IF(E14="CONTADO", 4%, IF(E14="TARJETA / CHEQUE", 3%, IF(OR(E14="FINANCIADO", E14="MCP"), 2.5%, ""))) -> 0.04 | G14: =IF(F14="", "", F14*D14) -> 60000 | H14: =TRUE() -> TRUE | I14: =TRUE() -> TRUE | J14: 46104 | K14: EXISTENTE
A15: 17 | B15: 46102 | C15: OPICHIANI JONATHAN | D15: 3275957.5 | E15: TARJETA / CHEQUE | F15: =IF(E15="CONTADO", 4%, IF(E15="TARJETA / CHEQUE", 3%, IF(OR(E15="FINANCIADO", E15="MCP"), 2.5%, ""))) -> 0.03 | G15: =IF(F15="", "", F15*D15) -> 98278.724 | H15: =TRUE() -> TRUE | I15: =TRUE() -> TRUE | J15: 46102 | K15: NUEVO
A16: 19 | B16: 46104 | C16: BARON ROCIO ANDREA | D16: 381621 | E16: CONTADO | F16: =IF(E16="CONTADO", 4%, IF(E16="TARJETA / CHEQUE", 3%, IF(OR(E16="FINANCIADO", E16="MCP"), 2.5%, ""))) -> 0.04 | G16: =IF(F16="", "", F16*D16) -> 15264.84 | H16: =TRUE() -> TRUE | I16: =TRUE() -> TRUE | J16: 46106 | K16: NUEVO
A17: 19 | B17: 46104 | C17: FLEITAS HOMAIRA SOLEDAD | D17: 2278777 | E17: TARJETA / CHEQUE | F17: =IF(E17="CONTADO", 4%, IF(E17="TARJETA / CHEQUE", 3%, IF(OR(E17="FINANCIADO", E17="MCP"), 2.5%, ""))) -> 0.03 | G17: =IF(F17="", "", F17*D17) -> 68363.31 | H17: =TRUE() -> TRUE | I17: =TRUE() -> TRUE | J17: 46107 | K17: NUEVO
A18: 22 | B18: 46107 | D18: 0 | E18: FINANCIADO | F18: =IF(E18="CONTADO", 4%, IF(E18="TARJETA / CHEQUE", 3%, IF(OR(E18="FINANCIADO", E18="MCP"), 2.5%, ""))) -> 0.025 | G18: =IF(F18="", "", F18*D18) -> 0 | H18: =FALSE() -> FALSE | I18: =FALSE() -> FALSE
F19: =IF(E19="CONTADO", 4%, IF(E19="TARJETA / CHEQUE", 3%, IF(OR(E19="FINANCIADO", E19="MCP"), 2.5%, ""))) | G19: =IF(F19="", "", F19*D19) | H19: =FALSE() -> FALSE | I19: =FALSE() -> FALSE
F20: =IF(E20="CONTADO", 4%, IF(E20="TARJETA / CHEQUE", 3%, IF(OR(E20="FINANCIADO", E20="MCP"), 2.5%, ""))) | G20: =IF(F20="", "", F20*D20) | H20: =FALSE() -> FALSE | I20: =FALSE() -> FALSE
F21: =IF(E21="CONTADO", 4%, IF(E21="TARJETA / CHEQUE", 3%, IF(OR(E21="FINANCIADO", E21="MCP"), 2.5%, ""))) | G21: =IF(F21="", "", F21*D21) | H21: =FALSE() -> FALSE | I21: =FALSE() -> FALSE
F22: =IF(E22="CONTADO", 4%, IF(E22="TARJETA / CHEQUE", 3%, IF(OR(E22="FINANCIADO", E22="MCP"), 2.5%, ""))) | G22: =IF(F22="", "", F22*D22) | H22: =FALSE() -> FALSE | I22: =FALSE() -> FALSE
F23: =IF(E23="CONTADO", 4%, IF(E23="TARJETA / CHEQUE", 3%, IF(OR(E23="FINANCIADO", E23="MCP"), 2.5%, ""))) | G23: =IF(F23="", "", F23*D23) | H23: =FALSE() -> FALSE | I23: =FALSE() -> FALSE
F24: =IF(E24="CONTADO", 4%, IF(E24="TARJETA / CHEQUE", 3%, IF(OR(E24="FINANCIADO", E24="MCP"), 2.5%, ""))) | G24: =IF(F24="", "", F24*D24) | H24: =FALSE() -> FALSE | I24: =FALSE() -> FALSE
F25: =IF(E25="CONTADO", 4%, IF(E25="TARJETA / CHEQUE", 3%, IF(OR(E25="FINANCIADO", E25="MCP"), 2.5%, ""))) | G25: =IF(F25="", "", F25*D25) | H25: =FALSE() -> FALSE | I25: =FALSE() -> FALSE
F26: =IF(E26="CONTADO", 4%, IF(E26="TARJETA / CHEQUE", 3%, IF(OR(E26="FINANCIADO", E26="MCP"), 2.5%, ""))) | G26: =IF(F26="", "", F26*D26) | H26: =FALSE() -> FALSE | I26: =FALSE() -> FALSE
F27: =IF(E27="CONTADO", 4%, IF(E27="TARJETA / CHEQUE", 3%, IF(OR(E27="FINANCIADO", E27="MCP"), 2.5%, ""))) | G27: =IF(F27="", "", F27*D27) | H27: =FALSE() -> FALSE | I27: =FALSE() -> FALSE
F28: =IF(E28="CONTADO", 4%, IF(E28="TARJETA / CHEQUE", 3%, IF(OR(E28="FINANCIADO", E28="MCP"), 2.5%, ""))) | G28: =IF(F28="", "", F28*D28) | H28: =FALSE() -> FALSE | I28: =FALSE() -> FALSE
F29: =IF(E29="CONTADO", 4%, IF(E29="TARJETA / CHEQUE", 3%, IF(OR(E29="FINANCIADO", E29="MCP"), 2.5%, ""))) | G29: =IF(F29="", "", F29*D29) | H29: =FALSE() -> FALSE | I29: =FALSE() -> FALSE
F30: =IF(E30="CONTADO", 4%, IF(E30="TARJETA / CHEQUE", 3%, IF(OR(E30="FINANCIADO", E30="MCP"), 2.5%, ""))) | G30: =IF(F30="", "", F30*D30) | H30: =FALSE() -> FALSE | I30: =FALSE() -> FALSE
... F1000: =IF(E1000="CONTADO", 4%, IF(E1000="TARJETA / CHEQUE", 3%, IF(OR(E1000="FINANCIADO", E1000="MCP"), 2.5%, ""))) | G1000: =IF(F1000="", "", F1000*D1000) | H1000: =FALSE() -> FALSE | I1000: =FALSE() -> FALSE

Sheet ABRIL 2026
A1: PERÍODO: 27/03 AL 30/04 | DÍAS HÁBILES: 23 | SÁBADOS (½): 5 | FERIADO: 1/2 día 02/04 + 1 día 03/04 | M1: TOTAL VENDIDO | N1: CONTADO | O1: TARJETA / CHEQUE | P1: FINANCIADO | Q1: MCP | R1: OBJETIVO MENSUAL | T1: MÍNIMO A VENDER
A2: N° DÍA | B2: FECHA DE VENTA | C2: APELLIDO Y NOMBRE | D2: MONTO FICHA | E2: FORMA | F2: COMISIÓN (%) | G2: COMISIÓN ($) | H2: ENTREGADO | I2: SISTEMA | J2: FECHA DE CARGA EN EL SISTEMA | K2: CLIENTE | M2: =SUM(D:D) -> 23654654 | N2: =SUMIF($E:$E,N1,$D:$D) -> 10120300 | O2: =SUMIF($E:$E,O1,$D:$D) -> 4695089.2 | P2: =SUMIF($E:$E,P1,$D:$D) -> 8839265 | Q2: =SUMIF($E:$E,Q1,$D:$D) -> 0 | R2: =M2/S2 -> 0.84480908 | S2: 28000000 | T2: =(N2+O2+P2+(Q2/2))/U2 -> 1.7418744 | U2: 13580000
A3: 1 | B3: 46108 | E3: CONTADO | F3: =IF(E3="CONTADO", 4%, IF(E3="TARJETA / CHEQUE", 3%, IF(E3="FINANCIADO", 2.5%, ""))) -> 0.04 | G3: =IF(F3="", "", F3*D3) -> 0 | H3: =FALSE() -> FALSE | I3: =FALSE() -> FALSE | R3: RESTANTE | S3: =S2-M2 -> 4345345.8 | T3: RESTANTE | U3: =IF((U2-M2)>=0,U2-M2,"")
E4: FINANCIADO | F4: =IF(E4="CONTADO", 4%, IF(E4="TARJETA / CHEQUE", 3%, IF(E4="FINANCIADO", 2.5%, ""))) -> 0.025 | G4: =IF(F4="", "", F4*D4) -> 0 | H4: =FALSE() -> FALSE | I4: =FALSE() -> FALSE
A5: Sáb | B5: 46109 | C5: MARIA CONCEPCION FERREYRA | D5: 145530 | E5: CONTADO | F5: =IF(E5="CONTADO", 4%, IF(E5="TARJETA / CHEQUE", 3%, IF(E5="FINANCIADO", 2.5%, ""))) -> 0.04 | G5: =IF(F5="", "", F5*D5) -> 5821.2 | H5: =TRUE() -> TRUE | I5: =TRUE() -> TRUE | J5: 46118 | K5: NUEVO | M5: LOCALIDAD | R5: COBRADOR | T5: ANTICIPO SI ES NUEVO
A6: 2 | B6: 46111 | C6: MARIA SOL MACENA | D6: 71644 | E6: CONTADO | F6: =IF(E6="CONTADO", 4%, IF(E6="TARJETA / CHEQUE", 3%, IF(E6="FINANCIADO", 2.5%, ""))) -> 0.04 | G6: =IF(F6="", "", F6*D6) -> 2865.76 | H6: =TRUE() -> TRUE | I6: =TRUE() -> TRUE | J6: 46112 | K6: NUEVO | M6: Cerro Azul | R6: =IFERROR(VLOOKUP(M6,BD!H:J,2,FALSE()),"") -> Hernán González - ZONA 2 | T6: =IFERROR(VLOOKUP(M6,BD!H:J,3,FALSE()),"") -> 1ER CUOTA
A7: 3 | B7: 46112 | C7: GUILLERMO BENITEZ | D7: 830450.96 | E7: TARJETA / CHEQUE | F7: =IF(E7="CONTADO", 4%, IF(E7="TARJETA / CHEQUE", 3%, IF(E7="FINANCIADO", 2.5%, ""))) -> 0.03 | G7: =IF(F7="", "", F7*D7) -> 24913.529 | H7: =TRUE() -> TRUE | I7: =TRUE() -> TRUE | J7: 46112 | K7: NUEVO
A8: 4 | B8: 46113 | F8: =IF(E8="CONTADO", 4%, IF(E8="TARJETA / CHEQUE", 3%, IF(E8="FINANCIADO", 2.5%, ""))) | G8: =IF(F8="", "", F8*D8) | H8: =FALSE() -> FALSE | I8: =FALSE() -> FALSE
A9: 1/2 día | B9: 46114 | F9: =IF(E9="CONTADO", 4%, IF(E9="TARJETA / CHEQUE", 3%, IF(E9="FINANCIADO", 2.5%, ""))) | G9: =IF(F9="", "", F9*D9) | H9: =FALSE() -> FALSE | I9: =FALSE() -> FALSE
A10: FERIADO | B10: 46115 | F10: =IF(E10="CONTADO", 4%, IF(E10="TARJETA / CHEQUE", 3%, IF(E10="FINANCIADO", 2.5%, ""))) | G10: =IF(F10="", "", F10*D10) | H10: =FALSE() -> FALSE | I10: =FALSE() -> FALSE
A11: Sáb | B11: 46116 | F11: =IF(E11="CONTADO", 4%, IF(E11="TARJETA / CHEQUE", 3%, IF(OR(E11="FINANCIADO", E11="MCP"), 2.5%, ""))) | G11: =IF(F11="", "", F11*D11) | H11: =FALSE() -> FALSE | I11: =FALSE() -> FALSE
A12: 5 | B12: 46118 | C12: VILLAR EMILIA | D12: 58160 | E12: FINANCIADO | F12: =IF(E12="CONTADO", 4%, IF(E12="TARJETA / CHEQUE", 3%, IF(OR(E12="FINANCIADO", E12="MCP"), 2.5%, ""))) -> 0.025 | G12: =IF(F12="", "", F12*D12) -> 1454 | H12: =TRUE() -> TRUE | I12: =TRUE() -> TRUE | J12: 46120 | K12: EXISTENTE
B13: 46118 | C13: DANIEL ALEJANDRO TINTA | D13: 3099750 | E13: FINANCIADO | F13: =IF(E13="CONTADO", 4%, IF(E13="TARJETA / CHEQUE", 3%, IF(OR(E13="FINANCIADO", E13="MCP"), 2.5%, ""))) -> 0.025 | G13: =IF(F13="", "", F13*D13) -> 77493.75 | H13: =TRUE() -> TRUE | I13: =TRUE() -> TRUE | J13: 46128 | K13: EXISTENTE
B14: 46118 | C14: CRISTIAN ARIEL DE OLIVEIRA | D14: 1435511 | E14: CONTADO | F14: =IF(E14="CONTADO", 4%, IF(E14="TARJETA / CHEQUE", 3%, IF(OR(E14="FINANCIADO", E14="MCP"), 2.5%, ""))) -> 0.04 | G14: =IF(F14="", "", F14*D14) -> 57420.44 | H14: =TRUE() -> TRUE | I14: =TRUE() -> TRUE | J14: 46121 | K14: NUEVO
A15: 6 | B15: 46119 | C15: CARLOS MARIA BLANCO | D15: 963979 | E15: CONTADO | F15: =IF(E15="CONTADO", 4%, IF(E15="TARJETA / CHEQUE", 3%, IF(OR(E15="FINANCIADO", E15="MCP"), 2.5%, ""))) -> 0.04 | G15: =IF(F15="", "", F15*D15) -> 38559.16 | H15: =TRUE() -> TRUE | I15: =TRUE() -> TRUE | J15: 46120 | K15: NUEVO
A16: 7 | B16: 46120 | C16: MONTENEGRO PATRICIA DEL CARMEN | D16: 1116220 | E16: FINANCIADO | F16: =IF(E16="CONTADO", 4%, IF(E16="TARJETA / CHEQUE", 3%, IF(OR(E16="FINANCIADO", E16="MCP"), 2.5%, ""))) -> 0.025 | G16: =IF(F16="", "", F16*D16) -> 27905.5 | H16: =TRUE() -> TRUE | I16: =TRUE() -> TRUE | J16: 46139 | K16: NUEVO
A17: 8 | B17: 46121 | F17: =IF(E17="CONTADO", 4%, IF(E17="TARJETA / CHEQUE", 3%, IF(OR(E17="FINANCIADO", E17="MCP"), 2.5%, ""))) | G17: =IF(F17="", "", F17*D17) | H17: =FALSE() -> FALSE | I17: =FALSE() -> FALSE
A18: 9 | B18: 46122 | F18: =IF(E18="CONTADO", 4%, IF(E18="TARJETA / CHEQUE", 3%, IF(OR(E18="FINANCIADO", E18="MCP"), 2.5%, ""))) | G18: =IF(F18="", "", F18*D18) | H18: =FALSE() -> FALSE | I18: =FALSE() -> FALSE
A19: Sáb | B19: 46123 | C19: HORODYSKI MARIA | D19: 1192110 | E19: CONTADO | F19: =IF(E19="CONTADO", 4%, IF(E19="TARJETA / CHEQUE", 3%, IF(OR(E19="FINANCIADO", E19="MCP"), 2.5%, ""))) -> 0.04 | G19: =IF(F19="", "", F19*D19) -> 47684.4 | H19: =TRUE() -> TRUE | I19: =TRUE() -> TRUE | J19: 46129 | K19: EXISTENTE
A20: 10 | B20: 46125 | F20: =IF(E20="CONTADO", 4%, IF(E20="TARJETA / CHEQUE", 3%, IF(OR(E20="FINANCIADO", E20="MCP"), 2.5%, ""))) | G20: =IF(F20="", "", F20*D20) | H20: =FALSE() -> FALSE | I20: =FALSE() -> FALSE
A21: 11 | B21: 46126 | C21: TOMAS AGUSTIN ROJAS | D21: 46733 | E21: CONTADO | F21: =IF(E21="CONTADO", 4%, IF(E21="TARJETA / CHEQUE", 3%, IF(OR(E21="FINANCIADO", E21="MCP"), 2.5%, ""))) -> 0.04 | G21: =IF(F21="", "", F21*D21) -> 1869.32 | H21: =TRUE() -> TRUE | I21: =TRUE() -> TRUE | J21: 46126 | K21: NUEVO
A22: 12 | B22: 46127 | C22: DANIEL EDUARDO TORREZ | D22: 650000 | E22: CONTADO | F22: =IF(E22="CONTADO", 4%, IF(E22="TARJETA / CHEQUE", 3%, IF(OR(E22="FINANCIADO", E22="MCP"), 2.5%, ""))) -> 0.04 | G22: =IF(F22="", "", F22*D22) -> 26000 | H22: =TRUE() -> TRUE | I22: =TRUE() -> TRUE | J22: 46127 | K22: NUEVO
A23: 13 | B23: 46128 | C23: SHORODER ARIEL HERNAN | D23: 2012000 | E23: CONTADO | F23: =IF(E23="CONTADO", 4%, IF(E23="TARJETA / CHEQUE", 3%, IF(OR(E23="FINANCIADO", E23="MCP"), 2.5%, ""))) -> 0.04 | G23: =IF(F23="", "", F23*D23) -> 80480 | H23: =TRUE() -> TRUE | I23: =TRUE() -> TRUE | J23: 46129 | K23: NUEVO
A24: 14 | B24: 46129 | F24: =IF(E24="CONTADO", 4%, IF(E24="TARJETA / CHEQUE", 3%, IF(OR(E24="FINANCIADO", E24="MCP"), 2.5%, ""))) | G24: =IF(F24="", "", F24*D24) | H24: =FALSE() -> FALSE | I24: =FALSE() -> FALSE
A25: Sáb | B25: 46130 | C25: TONARELLI FRANCISCO | D25: 606133 | E25: CONTADO | F25: =IF(E25="CONTADO", 4%, IF(E25="TARJETA / CHEQUE", 3%, IF(OR(E25="FINANCIADO", E25="MCP"), 2.5%, ""))) -> 0.04 | G25: =IF(F25="", "", F25*D25) -> 24245.32 | H25: =TRUE() -> TRUE | I25: =TRUE() -> TRUE | J25: 46132 | K25: NUEVO
A26: 15 | B26: 46132 | C26: LISANDRO SCARSO | D26: 1044310 | E26: CONTADO | F26: =IF(E26="CONTADO", 4%, IF(E26="TARJETA / CHEQUE", 3%, IF(OR(E26="FINANCIADO", E26="MCP"), 2.5%, ""))) -> 0.04 | G26: =IF(F26="", "", F26*D26) -> 41772.4 | H26: =TRUE() -> TRUE | I26: =TRUE() -> TRUE | J26: 46134 | K26: NUEVO
A27: 16 | B27: 46133 | F27: =IF(E27="CONTADO", 4%, IF(E27="TARJETA / CHEQUE", 3%, IF(OR(E27="FINANCIADO", E27="MCP"), 2.5%, ""))) | G27: =IF(F27="", "", F27*D27) | H27: =FALSE() -> FALSE | I27: =FALSE() -> FALSE
A28: 17 | B28: 46134 | C28: MARCOS NOIR | D28: 165000 | E28: CONTADO | F28: =IF(E28="CONTADO", 4%, IF(E28="TARJETA / CHEQUE", 3%, IF(OR(E28="FINANCIADO", E28="MCP"), 2.5%, ""))) -> 0.04 | G28: =IF(F28="", "", F28*D28) -> 6600 | H28: =TRUE() -> TRUE | I28: =TRUE() -> TRUE | J28: 46134 | K28: NUEVO
B29: 46134 | C29: MARIO SCOCCIA | D29: 1129860 | E29: CONTADO | F29: =IF(E29="CONTADO", 4%, IF(E29="TARJETA / CHEQUE", 3%, IF(OR(E29="FINANCIADO", E29="MCP"), 2.5%, ""))) -> 0.04 | G29: =IF(F29="", "", F29*D29) -> 45194.4 | H29: =TRUE() -> TRUE | I29: =TRUE() -> TRUE | J29: 46139 | K29: NUEVO
A30: 18 | B30: 46135 | C30: BONUS LEANDRO | D30: 548528.79 | E30: TARJETA / CHEQUE | F30: =IF(E30="CONTADO", 4%, IF(E30="TARJETA / CHEQUE", 3%, IF(OR(E30="FINANCIADO", E30="MCP"), 2.5%, ""))) -> 0.03 | G30: =IF(F30="", "", F30*D30) -> 16455.864 | H30: =TRUE() -> TRUE | I30: =TRUE() -> TRUE | J30: 46135 | K30: NUEVO
B31: 46135 | C31: MIERES MARIANO | D31: 1718330 | E31: FINANCIADO | F31: =IF(E31="CONTADO", 4%, IF(E31="TARJETA / CHEQUE", 3%, IF(OR(E31="FINANCIADO", E31="MCP"), 2.5%, ""))) -> 0.025 | G31: =IF(F31="", "", F31*D31) -> 42958.25 | H31: =TRUE() -> TRUE | I31: =TRUE() -> TRUE | J31: 46139 | K31: NUEVO
A32: 19 | B32: 46136 | F32: =IF(E32="CONTADO", 4%, IF(E32="TARJETA / CHEQUE", 3%, IF(OR(E32="FINANCIADO", E32="MCP"), 2.5%, ""))) | G32: =IF(F32="", "", F32*D32) | H32: =FALSE() -> FALSE | I32: =FALSE() -> FALSE
A33: Sáb | B33: 46137 | F33: =IF(E33="CONTADO", 4%, IF(E33="TARJETA / CHEQUE", 3%, IF(OR(E33="FINANCIADO", E33="MCP"), 2.5%, ""))) | G33: =IF(F33="", "", F33*D33) | H33: =FALSE() -> FALSE | I33: =FALSE() -> FALSE
A34: 20 | B34: 46139 | C34: LUISA FRANK | D34: 812176 | E34: TARJETA / CHEQUE | F34: =IF(E34="CONTADO", 4%, IF(E34="TARJETA / CHEQUE", 3%, IF(OR(E34="FINANCIADO", E34="MCP"), 2.5%, ""))) -> 0.03 | G34: =IF(F34="", "", F34*D34) -> 24365.28 | H34: =TRUE() -> TRUE | I34: =TRUE() -> TRUE | J34: 46139 | K34: NUEVO
A35: 20 | B35: 46139 | C35: LUISA FRANK | D35: 657490 | E35: CONTADO | F35: =IF(E35="CONTADO", 4%, IF(E35="TARJETA / CHEQUE", 3%, IF(OR(E35="FINANCIADO", E35="MCP"), 2.5%, ""))) -> 0.04 | G35: =IF(F35="", "", F35*D35) -> 26299.6 | H35: =FALSE() -> FALSE | I35: =FALSE() -> FALSE
A36: 21 | B36: 46140 | C36: RODOLFO DREWANZ | D36: 564445.65 | E36: TARJETA / CHEQUE | F36: =IF(E36="CONTADO", 4%, IF(E36="TARJETA / CHEQUE", 3%, IF(OR(E36="FINANCIADO", E36="MCP"), 2.5%, ""))) -> 0.03 | G36: =IF(F36="", "", F36*D36) -> 16933.37 | H36: =TRUE() -> TRUE | I36: =TRUE() -> TRUE | J36: 46140 | K36: NUEVO
B37: 46140 | C37: GOMEZ ANGEL | D37: 1714035 | E37: FINANCIADO | F37: =IF(E37="CONTADO", 4%, IF(E37="TARJETA / CHEQUE", 3%, IF(OR(E37="FINANCIADO", E37="MCP"), 2.5%, ""))) -> 0.025 | G37: =IF(F37="", "", F37*D37) -> 42850.875 | H37: =TRUE() -> TRUE | I37: =TRUE() -> TRUE | J37: 46142 | K37: EXISTENTE
A38: 22 | B38: 46141 | C38: MARTINEZ GUIDO | D38: 1132770 | E38: FINANCIADO | F38: =IF(E38="CONTADO", 4%, IF(E38="TARJETA / CHEQUE", 3%, IF(OR(E38="FINANCIADO", E38="MCP"), 2.5%, ""))) -> 0.025 | G38: =IF(F38="", "", F38*D38) -> 28319.25 | H38: =TRUE() -> TRUE | I38: =TRUE() -> TRUE | J38: 46142 | K38: NUEVO
B39: 46141 | C39: ROMINA SANTANA | D39: 143573 | E39: TARJETA / CHEQUE | F39: =IF(E39="CONTADO", 4%, IF(E39="TARJETA / CHEQUE", 3%, IF(OR(E39="FINANCIADO", E39="MCP"), 2.5%, ""))) -> 0.03 | G39: =IF(F39="", "", F39*D39) -> 4307.19 | H39: =TRUE() -> TRUE | I39: =TRUE() -> TRUE | J39: 46142 | K39: NUEVO
B40: 46141 | C40: BONUS LEANDRO | D40: 1046204.2 | E40: TARJETA / CHEQUE | F40: =IF(E40="CONTADO", 4%, IF(E40="TARJETA / CHEQUE", 3%, IF(OR(E40="FINANCIADO", E40="MCP"), 2.5%, ""))) -> 0.03 | G40: =IF(F40="", "", F40*D40) -> 31386.125 | H40: =TRUE() -> TRUE | I40: =TRUE() -> TRUE | J40: 46142 | K40: EXISTENTE
A41: 23 | B41: 46142 | C41: PABLO VELAZQUEZ | D41: 749710.61 | E41: TARJETA / CHEQUE | F41: =IF(E41="CONTADO", 4%, IF(E41="TARJETA / CHEQUE", 3%, IF(OR(E41="FINANCIADO", E41="MCP"), 2.5%, ""))) -> 0.03 | G41: =IF(F41="", "", F41*D41) -> 22491.318 | H41: =TRUE() -> TRUE | I41: =TRUE() -> TRUE | J41: 46142 | K41: EXISTENTE
B42: 46142 | C42: MEAURIO ENZO | D42: 0 | E42: FINANCIADO | H42: =FALSE() -> FALSE | I42: =FALSE() -> FALSE | K42: NUEVO
G43: =IF(F43="", "", F43*D43) | H43: =FALSE() -> FALSE | I43: =FALSE() -> FALSE
F44: =IF(E44="CONTADO", 4%, IF(E44="TARJETA / CHEQUE", 3%, IF(OR(E44="FINANCIADO", E44="MCP"), 2.5%, ""))) | G44: =IF(F44="", "", F44*D44) | H44: =FALSE() -> FALSE | I44: =FALSE() -> FALSE
F45: =IF(E45="CONTADO", 4%, IF(E45="TARJETA / CHEQUE", 3%, IF(OR(E45="FINANCIADO", E45="MCP"), 2.5%, ""))) | G45: =IF(F45="", "", F45*D45) | H45: =FALSE() -> FALSE | I45: =FALSE() -> FALSE
F46: =IF(E46="CONTADO", 4%, IF(E46="TARJETA / CHEQUE", 3%, IF(OR(E46="FINANCIADO", E46="MCP"), 2.5%, ""))) | G46: =IF(F46="", "", F46*D46) | H46: =FALSE() -> FALSE | I46: =FALSE() -> FALSE
F47: =IF(E47="CONTADO", 4%, IF(E47="TARJETA / CHEQUE", 3%, IF(OR(E47="FINANCIADO", E47="MCP"), 2.5%, ""))) | G47: =IF(F47="", "", F47*D47) | H47: =FALSE() -> FALSE | I47: =FALSE() -> FALSE
F48: =IF(E48="CONTADO", 4%, IF(E48="TARJETA / CHEQUE", 3%, IF(OR(E48="FINANCIADO", E48="MCP"), 2.5%, ""))) | G48: =IF(F48="", "", F48*D48) | H48: =FALSE() -> FALSE | I48: =FALSE() -> FALSE
F49: =IF(E49="CONTADO", 4%, IF(E49="TARJETA / CHEQUE", 3%, IF(OR(E49="FINANCIADO", E49="MCP"), 2.5%, ""))) | G49: =IF(F49="", "", F49*D49) | H49: =FALSE() -> FALSE | I49: =FALSE() -> FALSE
F50: =IF(E50="CONTADO", 4%, IF(E50="TARJETA / CHEQUE", 3%, IF(OR(E50="FINANCIADO", E50="MCP"), 2.5%, ""))) | G50: =IF(F50="", "", F50*D50) | H50: =FALSE() -> FALSE | I50: =FALSE() -> FALSE
F51: =IF(E51="CONTADO", 4%, IF(E51="TARJETA / CHEQUE", 3%, IF(OR(E51="FINANCIADO", E51="MCP"), 2.5%, ""))) | G51: =IF(F51="", "", F51*D51) | H51: =FALSE() -> FALSE | I51: =FALSE() -> FALSE
F52: =IF(E52="CONTADO", 4%, IF(E52="TARJETA / CHEQUE", 3%, IF(OR(E52="FINANCIADO", E52="MCP"), 2.5%, ""))) | G52: =IF(F52="", "", F52*D52) | H52: =FALSE() -> FALSE | I52: =FALSE() -> FALSE
F53: =IF(E53="CONTADO", 4%, IF(E53="TARJETA / CHEQUE", 3%, IF(OR(E53="FINANCIADO", E53="MCP"), 2.5%, ""))) | G53: =IF(F53="", "", F53*D53) | H53: =FALSE() -> FALSE | I53: =FALSE() -> FALSE
F54: =IF(E54="CONTADO", 4%, IF(E54="TARJETA / CHEQUE", 3%, IF(OR(E54="FINANCIADO", E54="MCP"), 2.5%, ""))) | G54: =IF(F54="", "", F54*D54) | H54: =FALSE() -> FALSE | I54: =FALSE() -> FALSE
F55: =IF(E55="CONTADO", 4%, IF(E55="TARJETA / CHEQUE", 3%, IF(OR(E55="FINANCIADO", E55="MCP"), 2.5%, ""))) | G55: =IF(F55="", "", F55*D55) | H55: =FALSE() -> FALSE | I55: =FALSE() -> FALSE
... F1009: =IF(E1009="CONTADO", 4%, IF(E1009="TARJETA / CHEQUE", 3%, IF(OR(E1009="FINANCIADO", E1009="MCP"), 2.5%, ""))) | G1009: =IF(F1009="", "", F1009*D1009) | H1009: =FALSE() -> FALSE | I1009: =FALSE() -> FALSE
H1010: =FALSE() -> FALSE | I1010: =FALSE() -> FALSE

Sheet MAYO 2026
A1: PERÍODO: 04/05 AL 28/05 | DÍAS HÁBILES: 18 | SÁBADOS (½): 2 | FERIADO: 1 día 25/05 | M1: TOTAL VENDIDO | N1: CONTADO | O1: TARJETA / CHEQUE | P1: FINANCIADO | Q1: MCP | R1: OBJETIVO MENSUAL | T1: MÍNIMO A VENDER
A2: N° DÍA | B2: FECHA DE VENTA | C2: APELLIDO Y NOMBRE | D2: MONTO FICHA | E2: FORMA | F2: COMISIÓN (%) | G2: COMISIÓN ($) | H2: ENTREGADO | I2: SISTEMA | J2: FECHA DE CARGA EN EL SISTEMA | K2: CLIENTE | M2: =SUM(D:D) -> 18218001 | N2: =SUMIF($E:$E,N1,$D:$D) -> 3937531 | O2: =SUMIF($E:$E,O1,$D:$D) -> 6404156 | P2: =SUMIF($E:$E,P1,$D:$D) -> 7876314 | Q2: =SUMIF($E:$E,Q1,$D:$D) -> 0 | R2: =M2/S2 -> 0.90089115 | S2: 20222200 | T2: =(N2+O2+P2+(Q2/2))/U2 -> 1.3249455 | U2: 13750000
A3: Sábado | B3: 46144 | C3: Zdanovich Alexander José | D3: 1118080 | E3: FINANCIADO | F3: =IF(E3="CONTADO", 4%, IF(E3="TARJETA / CHEQUE", 3%, IF(OR(E3="FINANCIADO", E3="MCP"), 2.5%, ""))) -> 0.025 | G3: =IF(F3="", "", F3*D3) -> 27952 | H3: =TRUE() -> TRUE | I3: =TRUE() -> TRUE | J3: 46153 | K3: NUEVO | R3: RESTANTE | S3: =S2-M2 -> 2004199 | T3: RESTANTE | U3: =IF((U2-M2)>=0,U2-M2,"")
A4: 1 | B4: 46146 | F4: =IF(E4="CONTADO", 4%, IF(E4="TARJETA / CHEQUE", 3%, IF(OR(E4="FINANCIADO", E4="MCP"), 2.5%, ""))) | G4: =IF(F4="", "", F4*D4) | H4: =FALSE() -> FALSE | I4: =FALSE() -> FALSE
A5: 2 | B5: 46147 | F5: =IF(E5="CONTADO", 4%, IF(E5="TARJETA / CHEQUE", 3%, IF(OR(E5="FINANCIADO", E5="MCP"), 2.5%, ""))) | G5: =IF(F5="", "", F5*D5) | H5: =FALSE() -> FALSE | I5: =FALSE() -> FALSE
A6: 3 | B6: 46148 | F6: =IF(E6="CONTADO", 4%, IF(E6="TARJETA / CHEQUE", 3%, IF(OR(E6="FINANCIADO", E6="MCP"), 2.5%, ""))) | G6: =IF(F6="", "", F6*D6) | H6: =FALSE() -> FALSE | I6: =FALSE() -> FALSE | M6: LOCALIDAD | R6: COBRADOR | T6: ANTICIPO SI ES NUEVO
A7: 4 | B7: 46149 | C7: Jansat Victor Ezequiel | D7: 517492 | E7: FINANCIADO | F7: =IF(E7="CONTADO", 4%, IF(E7="TARJETA / CHEQUE", 3%, IF(OR(E7="FINANCIADO", E7="MCP"), 2.5%, ""))) -> 0.025 | G7: =IF(F7="", "", F7*D7) -> 12937.3 | H7: =TRUE() -> TRUE | I7: =TRUE() -> TRUE | J7: 46160 | K7: EXISTENTE | M7: Apóstoles | R7: =IFERROR(VLOOKUP(M7,BD!H:J,2,FALSE()),"") -> Hernán González - ZONA 2 | T7: =IFERROR(VLOOKUP(M7,BD!H:J,3,FALSE()),"") -> 1ER CUOTA
B8: 46149 | C8: Jansat Victor Ezequiel | D8: 430792 | E8: FINANCIADO | F8: =IF(E8="CONTADO", 4%, IF(E8="TARJETA / CHEQUE", 3%, IF(OR(E8="FINANCIADO", E8="MCP"), 2.5%, ""))) -> 0.025 | G8: =IF(F8="", "", F8*D8) -> 10769.8 | H8: =TRUE() -> TRUE | I8: =TRUE() -> TRUE | J8: 46160 | K8: EXISTENTE
A9: 5 | B9: 46150 | F9: =IF(E9="CONTADO", 4%, IF(E9="TARJETA / CHEQUE", 3%, IF(OR(E9="FINANCIADO", E9="MCP"), 2.5%, ""))) | G9: =IF(F9="", "", F9*D9) | H9: =FALSE() -> FALSE | I9: =FALSE() -> FALSE
A10: sábado | B10: 46151 | F10: =IF(E10="CONTADO", 4%, IF(E10="TARJETA / CHEQUE", 3%, IF(OR(E10="FINANCIADO", E10="MCP"), 2.5%, ""))) | G10: =IF(F10="", "", F10*D10) | H10: =FALSE() -> FALSE | I10: =FALSE() -> FALSE
A11: 6 | B11: 46153 | F11: =IF(E11="CONTADO", 4%, IF(E11="TARJETA / CHEQUE", 3%, IF(OR(E11="FINANCIADO", E11="MCP"), 2.5%, ""))) | G11: =IF(F11="", "", F11*D11) | H11: =FALSE() -> FALSE | I11: =FALSE() -> FALSE
A12: 7 | B12: 46154 | C12: ASOCIACION DE LA MUJER | D12: 663481 | E12: CONTADO | F12: =IF(E12="CONTADO", 4%, IF(E12="TARJETA / CHEQUE", 3%, IF(OR(E12="FINANCIADO", E12="MCP"), 2.5%, ""))) -> 0.04 | G12: =IF(F12="", "", F12*D12) -> 26539.24 | H12: =TRUE() -> TRUE | I12: =TRUE() -> TRUE | J12: 46160 | K12: NUEVO
B13: 46154 | C13: ADOLFO SCHWEIG | D13: 847240 | E13: FINANCIADO | F13: =IF(E13="CONTADO", 4%, IF(E13="TARJETA / CHEQUE", 3%, IF(OR(E13="FINANCIADO", E13="MCP"), 2.5%, ""))) -> 0.025 | G13: =IF(F13="", "", F13*D13) -> 21181 | H13: =TRUE() -> TRUE | I13: =TRUE() -> TRUE | J13: 46157 | K13: NUEVO
A14: 8 | B14: 46155 | H14: =FALSE() -> FALSE | I14: =FALSE() -> FALSE
A15: 9 | B15: 46156 | F15: =IF(E15="CONTADO", 4%, IF(E15="TARJETA / CHEQUE", 3%, IF(OR(E15="FINANCIADO", E15="MCP"), 2.5%, ""))) | G15: =IF(F15="", "", F15*D15) | H15: =FALSE() -> FALSE | I15: =FALSE() -> FALSE
A16: 10 | B16: 46157 | F16: =IF(E16="CONTADO", 4%, IF(E16="TARJETA / CHEQUE", 3%, IF(OR(E16="FINANCIADO", E16="MCP"), 2.5%, ""))) | G16: =IF(F16="", "", F16*D16) | H16: =FALSE() -> FALSE | I16: =FALSE() -> FALSE
A17: Sábado | B17: 46158 | F17: =IF(E17="CONTADO", 4%, IF(E17="TARJETA / CHEQUE", 3%, IF(OR(E17="FINANCIADO", E17="MCP"), 2.5%, ""))) | G17: =IF(F17="", "", F17*D17) | H17: =FALSE() -> FALSE | I17: =FALSE() -> FALSE
A18: 11 | B18: 46160 | C18: JORGE AGUILAR POZZER | D18: 1935532.1 | E18: TARJETA / CHEQUE | F18: =IF(E18="CONTADO", 4%, IF(E18="TARJETA / CHEQUE", 3%, IF(OR(E18="FINANCIADO", E18="MCP"), 2.5%, ""))) -> 0.03 | G18: =IF(F18="", "", F18*D18) -> 58065.964 | H18: =FALSE() -> FALSE | I18: =TRUE() -> TRUE | J18: 46170
B19: 46160 | C19: ALTAMIRANO CLAUDIO | D19: 22080 | E19: CONTADO | F19: =IF(E19="CONTADO", 4%, IF(E19="TARJETA / CHEQUE", 3%, IF(OR(E19="FINANCIADO", E19="MCP"), 2.5%, ""))) -> 0.04 | G19: =IF(F19="", "", F19*D19) -> 883.2 | H19: =TRUE() -> TRUE | I19: =TRUE() -> TRUE | J19: 46160
B20: 46160 | C20: RIOS JORGE DANIEL | D20: 657470 | E20: FINANCIADO | F20: =IF(E20="CONTADO", 4%, IF(E20="TARJETA / CHEQUE", 3%, IF(OR(E20="FINANCIADO", E20="MCP"), 2.5%, ""))) -> 0.025 | G20: =IF(F20="", "", F20*D20) -> 16436.75 | H20: =TRUE() -> TRUE | I20: =TRUE() -> TRUE | J20: 46164
A21: 12 | B21: 46161 | C21: CRISTINA ALVEZ | D21: 763134.87 | E21: TARJETA / CHEQUE | F21: =IF(E21="CONTADO", 4%, IF(E21="TARJETA / CHEQUE", 3%, IF(OR(E21="FINANCIADO", E21="MCP"), 2.5%, ""))) -> 0.03 | G21: =IF(F21="", "", F21*D21) -> 22894.046 | H21: =TRUE() -> TRUE | I21: =TRUE() -> TRUE | J21: 46161
B22: 46161 | C22: YRMA SILVA | D22: 27050 | E22: CONTADO | F22: =IF(E22="CONTADO", 4%, IF(E22="TARJETA / CHEQUE", 3%, IF(OR(E22="FINANCIADO", E22="MCP"), 2.5%, ""))) -> 0.04 | G22: =IF(F22="", "", F22*D22) -> 1082 | H22: =TRUE() -> TRUE | I22: =TRUE() -> TRUE | J22: 46162
B23: 46161 | C23: RAMIREZ CAMILA | D23: 554000 | E23: CONTADO | F23: =IF(E23="CONTADO", 4%, IF(E23="TARJETA / CHEQUE", 3%, IF(OR(E23="FINANCIADO", E23="MCP"), 2.5%, ""))) -> 0.04 | G23: =IF(F23="", "", F23*D23) -> 22160 | H23: =TRUE() -> TRUE | I23: =TRUE() -> TRUE | J23: 46162
A24: 13 | B24: 46162 | C24: BRUNO BADARACCO | D24: 194400 | E24: CONTADO | F24: =IF(E24="CONTADO", 4%, IF(E24="TARJETA / CHEQUE", 3%, IF(OR(E24="FINANCIADO", E24="MCP"), 2.5%, ""))) -> 0.04 | G24: =IF(F24="", "", F24*D24) -> 7776 | H24: =TRUE() -> TRUE | I24: =TRUE() -> TRUE | J24: 46162
A25: 14 | B25: 46163 | C25: ALBERTO MOREYRA | D25: 494098.43 | E25: TARJETA / CHEQUE | F25: =IF(E25="CONTADO", 4%, IF(E25="TARJETA / CHEQUE", 3%, IF(OR(E25="FINANCIADO", E25="MCP"), 2.5%, ""))) -> 0.03 | G25: =IF(F25="", "", F25*D25) -> 14822.953 | H25: =TRUE() -> TRUE | I25: =TRUE() -> TRUE | J25: 46163
B26: 46163 | C26: PATRICIA MONTENEGRO | D26: 1848580 | E26: FINANCIADO | F26: =IF(E26="CONTADO", 4%, IF(E26="TARJETA / CHEQUE", 3%, IF(OR(E26="FINANCIADO", E26="MCP"), 2.5%, ""))) -> 0.025 | G26: =IF(F26="", "", F26*D26) -> 46214.5 | H26: =TRUE() -> TRUE | I26: =TRUE() -> TRUE | J26: 46170
B27: 46163 | C27: BORDON JULIA | D27: 368360 | E27: FINANCIADO | F27: =IF(E27="CONTADO", 4%, IF(E27="TARJETA / CHEQUE", 3%, IF(OR(E27="FINANCIADO", E27="MCP"), 2.5%, ""))) -> 0.025 | G27: =IF(F27="", "", F27*D27) -> 9209 | H27: =TRUE() -> TRUE | I27: =TRUE() -> TRUE | J27: 46170
A28: 15 | B28: 46164 | C28: LEANDRO FOSS | D28: 11372 | E28: CONTADO | F28: =IF(E28="CONTADO", 4%, IF(E28="TARJETA / CHEQUE", 3%, IF(OR(E28="FINANCIADO", E28="MCP"), 2.5%, ""))) -> 0.04 | G28: =IF(F28="", "", F28*D28) -> 454.88 | H28: =TRUE() -> TRUE | I28: =TRUE() -> TRUE | J28: 46164
B29: 46164 | C29: FATIMA GONZALEZ | D29: 368790 | E29: CONTADO | F29: =IF(E29="CONTADO", 4%, IF(E29="TARJETA / CHEQUE", 3%, IF(OR(E29="FINANCIADO", E29="MCP"), 2.5%, ""))) -> 0.04 | G29: =IF(F29="", "", F29*D29) -> 14751.6 | H29: =TRUE() -> TRUE | I29: =TRUE() -> TRUE | J29: 46170
A30: Sábado | B30: 46165 | F30: =IF(E30="CONTADO", 4%, IF(E30="TARJETA / CHEQUE", 3%, IF(OR(E30="FINANCIADO", E30="MCP"), 2.5%, ""))) | G30: =IF(F30="", "", F30*D30) | H30: =FALSE() -> FALSE | I30: =FALSE() -> FALSE
A31: feriado | B31: 46167 | F31: =IF(E31="CONTADO", 4%, IF(E31="TARJETA / CHEQUE", 3%, IF(OR(E31="FINANCIADO", E31="MCP"), 2.5%, ""))) | G31: =IF(F31="", "", F31*D31) | H31: =FALSE() -> FALSE | I31: =FALSE() -> FALSE
A32: 16 | B32: 46168 | C32: RAUL RODRIGUEZ | D32: 47450 | E32: CONTADO | F32: =IF(E32="CONTADO", 4%, IF(E32="TARJETA / CHEQUE", 3%, IF(OR(E32="FINANCIADO", E32="MCP"), 2.5%, ""))) -> 0.04 | G32: =IF(F32="", "", F32*D32) -> 1898 | H32: =TRUE() -> TRUE | I32: =TRUE() -> TRUE | J32: 46169
B33: 46168 | C33: BENITEZ DOS SANTOS FELIPE | D33: 407787.44 | E33: TARJETA / CHEQUE | F33: =IF(E33="CONTADO", 4%, IF(E33="TARJETA / CHEQUE", 3%, IF(OR(E33="FINANCIADO", E33="MCP"), 2.5%, ""))) -> 0.03 | G33: =IF(F33="", "", F33*D33) -> 12233.623 | H33: =TRUE() -> TRUE | I33: =TRUE() -> TRUE | J33: 46170
B34: 46168 | C34: GUSTAVO SKWARIZSKI | D34: 2803603.1 | E34: TARJETA / CHEQUE | F34: =IF(E34="CONTADO", 4%, IF(E34="TARJETA / CHEQUE", 3%, IF(OR(E34="FINANCIADO", E34="MCP"), 2.5%, ""))) -> 0.03 | G34: =IF(F34="", "", F34*D34) -> 84108.094 | H34: =TRUE() -> TRUE | I34: =TRUE() -> TRUE | J34: 46168
A35: 17 | B35: 46169 | F35: =IF(E35="CONTADO", 4%, IF(E35="TARJETA / CHEQUE", 3%, IF(OR(E35="FINANCIADO", E35="MCP"), 2.5%, ""))) | G35: =IF(F35="", "", F35*D35) | H35: =FALSE() -> FALSE | I35: =FALSE() -> FALSE
A36: 18 | B36: 46170 | C36: LUZMILA SIMONE | D36: 553888 | E36: CONTADO | F36: =IF(E36="CONTADO", 4%, IF(E36="TARJETA / CHEQUE", 3%, IF(OR(E36="FINANCIADO", E36="MCP"), 2.5%, ""))) -> 0.04 | G36: =IF(F36="", "", F36*D36) -> 22155.52 | H36: =FALSE() -> FALSE | I36: =TRUE() -> TRUE | J36: 46170
B37: 46170 | C37: MARIA ESPINOLA | D37: 1380000 | E37: CONTADO | F37: =IF(E37="CONTADO", 4%, IF(E37="TARJETA / CHEQUE", 3%, IF(OR(E37="FINANCIADO", E37="MCP"), 2.5%, ""))) -> 0.04 | G37: =IF(F37="", "", F37*D37) -> 55200 | H37: =TRUE() -> TRUE | I37: =TRUE() -> TRUE | J37: 46170
B38: 46170 | C38: AYALA RAQUEL | D38: 1188300 | E38: FINANCIADO | F38: =IF(E38="CONTADO", 4%, IF(E38="TARJETA / CHEQUE", 3%, IF(OR(E38="FINANCIADO", E38="MCP"), 2.5%, ""))) -> 0.025 | G38: =IF(F38="", "", F38*D38) -> 29707.5 | H38: =TRUE() -> TRUE | I38: =TRUE() -> TRUE | J38: 46170
B39: 46170 | C39: BEATRIZ LAPIEVE | D39: 115020 | E39: CONTADO | F39: =IF(E39="CONTADO", 4%, IF(E39="TARJETA / CHEQUE", 3%, IF(OR(E39="FINANCIADO", E39="MCP"), 2.5%, ""))) -> 0.04 | G39: =IF(F39="", "", F39*D39) -> 4600.8 | H39: =TRUE() -> TRUE | I39: =TRUE() -> TRUE | J39: 46170
B40: 46170 | C40: LEOPOLDINO ARIEL | D40: 900000 | E40: FINANCIADO | F40: =IF(E40="CONTADO", 4%, IF(E40="TARJETA / CHEQUE", 3%, IF(OR(E40="FINANCIADO", E40="MCP"), 2.5%, ""))) -> 0.025 | G40: =IF(F40="", "", F40*D40) -> 22500 | H40: =TRUE() -> TRUE | I40: =TRUE() -> TRUE | J40: 46170
F41: =IF(E41="CONTADO", 4%, IF(E41="TARJETA / CHEQUE", 3%, IF(OR(E41="FINANCIADO", E41="MCP"), 2.5%, ""))) | G41: =IF(F41="", "", F41*D41) | H41: =FALSE() -> FALSE | I41: =FALSE() -> FALSE
F42: =IF(E42="CONTADO", 4%, IF(E42="TARJETA / CHEQUE", 3%, IF(OR(E42="FINANCIADO", E42="MCP"), 2.5%, ""))) | G42: =IF(F42="", "", F42*D42) | H42: =FALSE() -> FALSE | I42: =FALSE() -> FALSE
F43: =IF(E43="CONTADO", 4%, IF(E43="TARJETA / CHEQUE", 3%, IF(OR(E43="FINANCIADO", E43="MCP"), 2.5%, ""))) | G43: =IF(F43="", "", F43*D43) | H43: =FALSE() -> FALSE | I43: =FALSE() -> FALSE
F44: =IF(E44="CONTADO", 4%, IF(E44="TARJETA / CHEQUE", 3%, IF(OR(E44="FINANCIADO", E44="MCP"), 2.5%, ""))) | G44: =IF(F44="", "", F44*D44) | H44: =FALSE() -> FALSE | I44: =FALSE() -> FALSE
F45: =IF(E45="CONTADO", 4%, IF(E45="TARJETA / CHEQUE", 3%, IF(OR(E45="FINANCIADO", E45="MCP"), 2.5%, ""))) | G45: =IF(F45="", "", F45*D45) | H45: =FALSE() -> FALSE | I45: =FALSE() -> FALSE
F46: =IF(E46="CONTADO", 4%, IF(E46="TARJETA / CHEQUE", 3%, IF(OR(E46="FINANCIADO", E46="MCP"), 2.5%, ""))) | G46: =IF(F46="", "", F46*D46) | H46: =FALSE() -> FALSE | I46: =FALSE() -> FALSE
F47: =IF(E47="CONTADO", 4%, IF(E47="TARJETA / CHEQUE", 3%, IF(OR(E47="FINANCIADO", E47="MCP"), 2.5%, ""))) | G47: =IF(F47="", "", F47*D47) | H47: =FALSE() -> FALSE | I47: =FALSE() -> FALSE
F48: =IF(E48="CONTADO", 4%, IF(E48="TARJETA / CHEQUE", 3%, IF(OR(E48="FINANCIADO", E48="MCP"), 2.5%, ""))) | G48: =IF(F48="", "", F48*D48) | H48: =FALSE() -> FALSE | I48: =FALSE() -> FALSE
F49: =IF(E49="CONTADO", 4%, IF(E49="TARJETA / CHEQUE", 3%, IF(OR(E49="FINANCIADO", E49="MCP"), 2.5%, ""))) | G49: =IF(F49="", "", F49*D49) | H49: =FALSE() -> FALSE | I49: =FALSE() -> FALSE
F50: =IF(E50="CONTADO", 4%, IF(E50="TARJETA / CHEQUE", 3%, IF(OR(E50="FINANCIADO", E50="MCP"), 2.5%, ""))) | G50: =IF(F50="", "", F50*D50) | H50: =FALSE() -> FALSE | I50: =FALSE() -> FALSE
F51: =IF(E51="CONTADO", 4%, IF(E51="TARJETA / CHEQUE", 3%, IF(OR(E51="FINANCIADO", E51="MCP"), 2.5%, ""))) | G51: =IF(F51="", "", F51*D51) | H51: =FALSE() -> FALSE | I51: =FALSE() -> FALSE
F52: =IF(E52="CONTADO", 4%, IF(E52="TARJETA / CHEQUE", 3%, IF(OR(E52="FINANCIADO", E52="MCP"), 2.5%, ""))) | G52: =IF(F52="", "", F52*D52) | H52: =FALSE() -> FALSE | I52: =FALSE() -> FALSE
... F229: =IF(E229="CONTADO", 4%, IF(E229="TARJETA / CHEQUE", 3%, IF(OR(E229="FINANCIADO", E229="MCP"), 2.5%, ""))) | G229: =IF(F229="", "", F229*D229) | H229: =FALSE() -> FALSE | I229: =FALSE() -> FALSE
H230: =FALSE() -> FALSE | I230: =FALSE() -> FALSE
H231: =FALSE() -> FALSE | I231: =FALSE() -> FALSE
H232: =FALSE() -> FALSE | I232: =FALSE() -> FALSE
H233: =FALSE() -> FALSE | I233: =FALSE() -> FALSE
H234: =FALSE() -> FALSE | I234: =FALSE() -> FALSE
H235: =FALSE() -> FALSE | I235: =FALSE() -> FALSE
H236: =FALSE() -> FALSE | I236: =FALSE() -> FALSE
H237: =FALSE() -> FALSE | I237: =FALSE() -> FALSE
H238: =FALSE() -> FALSE | I238: =FALSE() -> FALSE
H239: =FALSE() -> FALSE | I239: =FALSE() -> FALSE
H240: =FALSE() -> FALSE | I240: =FALSE() -> FALSE
H241: =FALSE() -> FALSE | I241: =FALSE() -> FALSE
... H1029: =FALSE() -> FALSE | I1029: =FALSE() -> FALSE

Sheet PLANTILLA BASE
A1: PERÍODO: 29/05 AL 25/06 | DÍAS HÁBILES: 19 | SÁBADOS (½): 0 | FERIADO: 1 día 15/06 | M1: TOTAL VENDIDO | N1: CONTADO | O1: TARJETA / CHEQUE | P1: FINANCIADO | Q1: MCP | R1: OBJETIVO MENSUAL | T1: MÍNIMO A VENDER
A2: N° DÍA | B2: FECHA DE VENTA | C2: APELLIDO Y NOMBRE | D2: MONTO FICHA | E2: FORMA | F2: COMISIÓN (%) | G2: COMISIÓN ($) | H2: ENTREGADO | I2: SISTEMA | J2: FECHA DE CARGA EN EL SISTEMA | K2: CLIENTE | M2: =SUM(D:D) -> 1665259.1 | N2: =SUMIF($E:$E,N1,$D:$D) -> 898974 | O2: =SUMIF($E:$E,O1,$D:$D) -> 196265.1 | P2: =SUMIF($E:$E,P1,$D:$D) -> 570020 | Q2: =SUMIF($E:$E,Q1,$D:$D) -> 0 | R2: =M2/S2 -> 0.059473539 | S2: 28000000 | T2: =(N2+O2+P2+(Q2/2))/U2 -> 0.12110975 | U2: 13750000
A3: 1 | B3: 46171 | C3: BEATRIZ LAPIEVE | D3: 76680 | E3: CONTADO | F3: =IF(E3="CONTADO", 4%, IF(E3="TARJETA / CHEQUE", 3%, IF(OR(E3="FINANCIADO", E3="MCP"), 2.5%, ""))) -> 0.04 | G3: =IF(F3="", "", F3*D3) -> 3067.2 | H3: =TRUE() -> TRUE | I3: =FALSE() -> FALSE | K3: EXISTENTE | R3: RESTANTE | S3: =S2-M2 -> 26334741 | T3: RESTANTE | U3: =IF((U2-M2)>=0,U2-M2,"") -> 12084741
B4: 46171 | C4: MARIANO MIERES | D4: 430540 | E4: FINANCIADO | F4: =IF(E4="CONTADO", 4%, IF(E4="TARJETA / CHEQUE", 3%, IF(OR(E4="FINANCIADO", E4="MCP"), 2.5%, ""))) -> 0.025 | G4: =IF(F4="", "", F4*D4) -> 10763.5 | H4: =FALSE() -> FALSE | I4: =FALSE() -> FALSE | K4: EXISTENTE
B5: 46171 | C5: SONIA PEREZ | D5: 196265.1 | E5: TARJETA / CHEQUE | F5: =IF(E5="CONTADO", 4%, IF(E5="TARJETA / CHEQUE", 3%, IF(OR(E5="FINANCIADO", E5="MCP"), 2.5%, ""))) -> 0.03 | G5: =IF(F5="", "", F5*D5) -> 5887.953 | H5: =TRUE() -> TRUE | I5: =FALSE() -> FALSE | K5: NUEVO | M5: LOCALIDAD | R5: COBRADOR | T5: ANTICIPO SI ES NUEVO
A6: Sábado | B6: 46172 | F6: =IF(E6="CONTADO", 4%, IF(E6="TARJETA / CHEQUE", 3%, IF(OR(E6="FINANCIADO", E6="MCP"), 2.5%, ""))) | G6: =IF(F6="", "", F6*D6) | H6: =FALSE() -> FALSE | I6: =FALSE() -> FALSE | M6: Santo Tomé (Corrientes) | R6: =IFERROR(VLOOKUP(M6,BD!H:J,2,FALSE()),"") -> Online - ZONA 20 | T6: =IFERROR(VLOOKUP(M6,BD!H:J,3,FALSE()),"") -> 30%
A7: 2 | B7: 46174 | C7: FLORENCIA MONTENEGRO | D7: 136000 | E7: CONTADO | F7: =IF(E7="CONTADO", 4%, IF(E7="TARJETA / CHEQUE", 3%, IF(OR(E7="FINANCIADO", E7="MCP"), 2.5%, ""))) -> 0.04 | G7: =IF(F7="", "", F7*D7) -> 5440 | H7: =FALSE() -> FALSE | I7: =FALSE() -> FALSE
A8: 3 | B8: 46175 | F8: =IF(E8="CONTADO", 4%, IF(E8="TARJETA / CHEQUE", 3%, IF(OR(E8="FINANCIADO", E8="MCP"), 2.5%, ""))) | G8: =IF(F8="", "", F8*D8) | H8: =FALSE() -> FALSE | I8: =FALSE() -> FALSE
A9: 4 | B9: 46176 | F9: =IF(E9="CONTADO", 4%, IF(E9="TARJETA / CHEQUE", 3%, IF(OR(E9="FINANCIADO", E9="MCP"), 2.5%, ""))) | G9: =IF(F9="", "", F9*D9) | H9: =FALSE() -> FALSE | I9: =FALSE() -> FALSE
A10: 5 | B10: 46177 | F10: =IF(E10="CONTADO", 4%, IF(E10="TARJETA / CHEQUE", 3%, IF(OR(E10="FINANCIADO", E10="MCP"), 2.5%, ""))) | G10: =IF(F10="", "", F10*D10) | H10: =FALSE() -> FALSE | I10: =FALSE() -> FALSE
A11: 6 | B11: 46178 | C11: MARCELINO CRISTALDO | D11: 358850 | E11: CONTADO | F11: =IF(E11="CONTADO", 4%, IF(E11="TARJETA / CHEQUE", 3%, IF(OR(E11="FINANCIADO", E11="MCP"), 2.5%, ""))) -> 0.04 | G11: =IF(F11="", "", F11*D11) -> 14354 | H11: =FALSE() -> FALSE | I11: =FALSE() -> FALSE
B12: 46178 | C12: AGUSTIN ANZUTE | D12: 327444 | E12: CONTADO | H12: =FALSE() -> FALSE | I12: =FALSE() -> FALSE
A13: Sábado | B13: 46179 | C13: ENCINA JUAN PABLO | D13: 139480 | E13: FINANCIADO | F13: =IF(E13="CONTADO", 4%, IF(E13="TARJETA / CHEQUE", 3%, IF(OR(E13="FINANCIADO", E13="MCP"), 2.5%, ""))) -> 0.025 | G13: =IF(F13="", "", F13*D13) -> 3487 | H13: =FALSE() -> FALSE | I13: =FALSE() -> FALSE
A14: 7 | B14: 46181 | F14: =IF(E14="CONTADO", 4%, IF(E14="TARJETA / CHEQUE", 3%, IF(OR(E14="FINANCIADO", E14="MCP"), 2.5%, ""))) | G14: =IF(F14="", "", F14*D14) | H14: =FALSE() -> FALSE | I14: =FALSE() -> FALSE
A15: 8 | B15: 46182 | F15: =IF(E15="CONTADO", 4%, IF(E15="TARJETA / CHEQUE", 3%, IF(OR(E15="FINANCIADO", E15="MCP"), 2.5%, ""))) | G15: =IF(F15="", "", F15*D15) | H15: =FALSE() -> FALSE | I15: =FALSE() -> FALSE
A16: 9 | B16: 46183 | F16: =IF(E16="CONTADO", 4%, IF(E16="TARJETA / CHEQUE", 3%, IF(OR(E16="FINANCIADO", E16="MCP"), 2.5%, ""))) | G16: =IF(F16="", "", F16*D16) | H16: =FALSE() -> FALSE | I16: =FALSE() -> FALSE
A17: 10 | B17: 46184 | H17: =FALSE() -> FALSE | I17: =FALSE() -> FALSE
A18: 11 | B18: 46185 | F18: =IF(E18="CONTADO", 4%, IF(E18="TARJETA / CHEQUE", 3%, IF(OR(E18="FINANCIADO", E18="MCP"), 2.5%, ""))) | G18: =IF(F18="", "", F18*D18) | H18: =FALSE() -> FALSE | I18: =FALSE() -> FALSE
A19: Sábado | B19: 46186 | F19: =IF(E19="CONTADO", 4%, IF(E19="TARJETA / CHEQUE", 3%, IF(OR(E19="FINANCIADO", E19="MCP"), 2.5%, ""))) | G19: =IF(F19="", "", F19*D19) | H19: =FALSE() -> FALSE | I19: =FALSE() -> FALSE
A20: FERIADO | B20: 46188 | F20: =IF(E20="CONTADO", 4%, IF(E20="TARJETA / CHEQUE", 3%, IF(OR(E20="FINANCIADO", E20="MCP"), 2.5%, ""))) | G20: =IF(F20="", "", F20*D20) | H20: =FALSE() -> FALSE | I20: =FALSE() -> FALSE
A21: 12 | B21: 46189 | F21: =IF(E21="CONTADO", 4%, IF(E21="TARJETA / CHEQUE", 3%, IF(OR(E21="FINANCIADO", E21="MCP"), 2.5%, ""))) | G21: =IF(F21="", "", F21*D21) | H21: =FALSE() -> FALSE | I21: =FALSE() -> FALSE
A22: 13 | B22: 46190 | F22: =IF(E22="CONTADO", 4%, IF(E22="TARJETA / CHEQUE", 3%, IF(OR(E22="FINANCIADO", E22="MCP"), 2.5%, ""))) | G22: =IF(F22="", "", F22*D22) | H22: =FALSE() -> FALSE | I22: =FALSE() -> FALSE
A23: 14 | B23: 46191 | F23: =IF(E23="CONTADO", 4%, IF(E23="TARJETA / CHEQUE", 3%, IF(OR(E23="FINANCIADO", E23="MCP"), 2.5%, ""))) | G23: =IF(F23="", "", F23*D23) | H23: =FALSE() -> FALSE | I23: =FALSE() -> FALSE
A24: 15 | B24: 46192 | F24: =IF(E24="CONTADO", 4%, IF(E24="TARJETA / CHEQUE", 3%, IF(OR(E24="FINANCIADO", E24="MCP"), 2.5%, ""))) | G24: =IF(F24="", "", F24*D24) | H24: =FALSE() -> FALSE | I24: =FALSE() -> FALSE
A25: Sábado | B25: 46193 | F25: =IF(E25="CONTADO", 4%, IF(E25="TARJETA / CHEQUE", 3%, IF(OR(E25="FINANCIADO", E25="MCP"), 2.5%, ""))) | G25: =IF(F25="", "", F25*D25) | H25: =FALSE() -> FALSE | I25: =FALSE() -> FALSE
A26: 16 | B26: 46195 | F26: =IF(E26="CONTADO", 4%, IF(E26="TARJETA / CHEQUE", 3%, IF(OR(E26="FINANCIADO", E26="MCP"), 2.5%, ""))) | G26: =IF(F26="", "", F26*D26) | H26: =FALSE() -> FALSE | I26: =FALSE() -> FALSE
A27: 17 | B27: 46196 | F27: =IF(E27="CONTADO", 4%, IF(E27="TARJETA / CHEQUE", 3%, IF(OR(E27="FINANCIADO", E27="MCP"), 2.5%, ""))) | G27: =IF(F27="", "", F27*D27) | H27: =FALSE() -> FALSE | I27: =FALSE() -> FALSE
A28: 18 | B28: 46197 | F28: =IF(E28="CONTADO", 4%, IF(E28="TARJETA / CHEQUE", 3%, IF(OR(E28="FINANCIADO", E28="MCP"), 2.5%, ""))) | G28: =IF(F28="", "", F28*D28) | H28: =FALSE() -> FALSE | I28: =FALSE() -> FALSE
A29: 19 | B29: 46198 | F29: =IF(E29="CONTADO", 4%, IF(E29="TARJETA / CHEQUE", 3%, IF(OR(E29="FINANCIADO", E29="MCP"), 2.5%, ""))) | G29: =IF(F29="", "", F29*D29) | H29: =FALSE() -> FALSE | I29: =FALSE() -> FALSE
F30: =IF(E30="CONTADO", 4%, IF(E30="TARJETA / CHEQUE", 3%, IF(OR(E30="FINANCIADO", E30="MCP"), 2.5%, ""))) | G30: =IF(F30="", "", F30*D30) | H30: =FALSE() -> FALSE | I30: =FALSE() -> FALSE
F31: =IF(E31="CONTADO", 4%, IF(E31="TARJETA / CHEQUE", 3%, IF(OR(E31="FINANCIADO", E31="MCP"), 2.5%, ""))) | G31: =IF(F31="", "", F31*D31) | H31: =FALSE() -> FALSE | I31: =FALSE() -> FALSE
F32: =IF(E32="CONTADO", 4%, IF(E32="TARJETA / CHEQUE", 3%, IF(OR(E32="FINANCIADO", E32="MCP"), 2.5%, ""))) | G32: =IF(F32="", "", F32*D32) | H32: =FALSE() -> FALSE | I32: =FALSE() -> FALSE
F33: =IF(E33="CONTADO", 4%, IF(E33="TARJETA / CHEQUE", 3%, IF(OR(E33="FINANCIADO", E33="MCP"), 2.5%, ""))) | G33: =IF(F33="", "", F33*D33) | H33: =FALSE() -> FALSE | I33: =FALSE() -> FALSE
F34: =IF(E34="CONTADO", 4%, IF(E34="TARJETA / CHEQUE", 3%, IF(OR(E34="FINANCIADO", E34="MCP"), 2.5%, ""))) | G34: =IF(F34="", "", F34*D34) | H34: =FALSE() -> FALSE | I34: =FALSE() -> FALSE
F35: =IF(E35="CONTADO", 4%, IF(E35="TARJETA / CHEQUE", 3%, IF(OR(E35="FINANCIADO", E35="MCP"), 2.5%, ""))) | G35: =IF(F35="", "", F35*D35) | H35: =FALSE() -> FALSE | I35: =FALSE() -> FALSE
F36: =IF(E36="CONTADO", 4%, IF(E36="TARJETA / CHEQUE", 3%, IF(OR(E36="FINANCIADO", E36="MCP"), 2.5%, ""))) | G36: =IF(F36="", "", F36*D36) | H36: =FALSE() -> FALSE | I36: =FALSE() -> FALSE
F37: =IF(E37="CONTADO", 4%, IF(E37="TARJETA / CHEQUE", 3%, IF(OR(E37="FINANCIADO", E37="MCP"), 2.5%, ""))) | G37: =IF(F37="", "", F37*D37) | H37: =FALSE() -> FALSE | I37: =FALSE() -> FALSE
F38: =IF(E38="CONTADO", 4%, IF(E38="TARJETA / CHEQUE", 3%, IF(OR(E38="FINANCIADO", E38="MCP"), 2.5%, ""))) | G38: =IF(F38="", "", F38*D38) | H38: =FALSE() -> FALSE | I38: =FALSE() -> FALSE
F39: =IF(E39="CONTADO", 4%, IF(E39="TARJETA / CHEQUE", 3%, IF(OR(E39="FINANCIADO", E39="MCP"), 2.5%, ""))) | G39: =IF(F39="", "", F39*D39) | H39: =FALSE() -> FALSE | I39: =FALSE() -> FALSE
F40: =IF(E40="CONTADO", 4%, IF(E40="TARJETA / CHEQUE", 3%, IF(OR(E40="FINANCIADO", E40="MCP"), 2.5%, ""))) | G40: =IF(F40="", "", F40*D40) | H40: =FALSE() -> FALSE | I40: =FALSE() -> FALSE
F41: =IF(E41="CONTADO", 4%, IF(E41="TARJETA / CHEQUE", 3%, IF(OR(E41="FINANCIADO", E41="MCP"), 2.5%, ""))) | G41: =IF(F41="", "", F41*D41) | H41: =FALSE() -> FALSE | I41: =FALSE() -> FALSE
... F232: =IF(E232="CONTADO", 4%, IF(E232="TARJETA / CHEQUE", 3%, IF(OR(E232="FINANCIADO", E232="MCP"), 2.5%, ""))) | G232: =IF(F232="", "", F232*D232) | H232: =FALSE() -> FALSE | I232: =FALSE() -> FALSE
H233: =FALSE() -> FALSE | I233: =FALSE() -> FALSE
H234: =FALSE() -> FALSE | I234: =FALSE() -> FALSE
H235: =FALSE() -> FALSE | I235: =FALSE() -> FALSE
H236: =FALSE() -> FALSE | I236: =FALSE() -> FALSE
H237: =FALSE() -> FALSE | I237: =FALSE() -> FALSE
H238: =FALSE() -> FALSE | I238: =FALSE() -> FALSE
H239: =FALSE() -> FALSE | I239: =FALSE() -> FALSE
H240: =FALSE() -> FALSE | I240: =FALSE() -> FALSE
H241: =FALSE() -> FALSE | I241: =FALSE() -> FALSE
H242: =FALSE() -> FALSE | I242: =FALSE() -> FALSE
H243: =FALSE() -> FALSE | I243: =FALSE() -> FALSE
H244: =FALSE() -> FALSE | I244: =FALSE() -> FALSE
... H1033: =FALSE() -> FALSE | I1033: =FALSE() -> FALSE

Sheet BD
A1: Medio | B1: Origen | C1: Venta Cerrada | D1: CRM | E1: Cliente | H1: LOCALIDADES | I1: COBRADOR | J1: ANTICIPO SI NO ES CLIENTE
A2: Online | B2: WhatsApp Directo | C2: Sí | D2: Sí | E2: Existente | H2: 25 de mayo | I2: Online - ZONA 20 | J2: 30%
A3: Salón | B3: Seguimiento WhatsApp | C3: No | D3: No | E3: Nuevo | H3: 2 de mayo | I3: Online - ZONA 20 | J3: 30%
A4: Llamada | B4: Referidos | H4: 9 de julio | I4: Online - ZONA 20 | J4: 30%
B5: Campaña RRSS | H5: Alba Posse | I5: Online - ZONA 20 | J5: 30%
B6: Marketplace Face | H6: Almafuerte | I6: Online - ZONA 20 | J6: 30%
B7: Instagram Asesor | H7: Andresito | I7: Online - ZONA 20 | J7: 30%
B8: Salón | H8: Apóstoles | I8: Hernán González - ZONA 2 | J8: 1ER CUOTA
B9: Google | H9: Aristóbulo del Valle | I9: Online - ZONA 20 | J9: 30%
H10: Azara | I10: Hernán González - ZONA 2 | J10: 1ER CUOTA
H11: Bernardo de Irigoyen | I11: Online - ZONA 20 | J11: 30%
H12: Bonpland | I12: Hernán González - ZONA 2 | J12: 1ER CUOTA
H13: Campo Grande | I13: Online - ZONA 20 | J13: 30%
H14: Campo Ramón | I14: Online - ZONA 20 | J14: 30%
H15: Campo Viera | I15: Online - ZONA 20 | J15: 30%
H16: Candelaria | I16: Hernán González - ZONA 2 | J16: 30%
H17: Capioví | I17: Marcelo Herrera - ZONA 4 | J17: 1ER CUOTA
H18: Caraguatay | I18: Online - ZONA 20 | J18: 30%
H19: Centinela | I19: Online - ZONA 20 | J19: 30%
H20: Cerro Azul | I20: Hernán González - ZONA 2 | J20: 1ER CUOTA
H21: Cerro Corá | I21: Hernán González - ZONA 2 | J21: 1ER CUOTA
... H80: Colonia Liebig (Corrientes) | I80: Hernán González - ZONA 2 | J80: 1ER CUOTA
